Workbook

Sheet Main
A1: Service Code | B1: SERV_PANEL_NAME | C1: S_DATE | D1: E_DATE | E1: Open/Closed | F1: Type | G1: ประเภทบริการ | H1: Agency Category | I1: Flow Type | J1: Barcode | K1: No. of fields | L1: คู่ค้า | M1: ค่าธรรมเนียม (Fee) | N1: AMOUNT MIN | O1: AMOUNT MAX | P1: PER DAY | Q1: ใบรับเงิน/ ใบกำกับภาษีอย่างย่อ | R1: ใบรับเงิน/ ใบกำกับภาษีเต็มรูป | S1: Tax Code | T1: ใบรับเงิน | U1: วันที่มีรายการล่าสุด | V1: STAT 2023 | W1: STAT 2023/m | X1: STAT 2023/Priority | Y1: STAT 2022 | Z1: STAT 2022/m | AA1: STAT 2022/Priority | AB1: STAT 2021 | AC1: STAT 2021/m | AD1: STAT 2021/Priority | AE1: STAT 2023-2021/Average | AF1: Priority/Sum | AG1: ใบขอใช้บริการ | AH1: ใบบันทึกรายการ | AI1: Comment
A2: 102 | B2: อิออน สินเชื่อ ยัวร์แคช OffLine | C2: 42186 | E2: Closed | F2: OFFLINE | G2: บริการรับชำระ | M2: 0 | N2: 0 | O2: 0 | P2: 100000 | T2: YES | U2: #N/A | V2: =VLOOKUP(A2,'2023 Stats'!$B$2:$D$192,3,FALSE) -> #N/A | W2: #N/A | Y2: #N/A | Z2: #N/A | AB2: #N/A | AE2: #N/A
A3: 103 | B3: จ่ายเงินบริการ KBANK2POST ของ ธ.กสิกรไทย | C3: 42186 | E3: Closed | F3: OFFLINE | G3: บริการรับชำระ | M3: 0 | N3: 0 | O3: 0 | P3: 100000 | T3: YES | U3: #N/A | V3: =VLOOKUP(A3,'2023 Stats'!$B$2:$D$192,3,FALSE) -> #N/A | W3: #N/A | Y3: #N/A | Z3: #N/A | AB3: #N/A | AE3: #N/A
A4: 104 | B4: รับเงินฝาก ธ.ไทยเครดิต (บาร์โค้ด) Offline | C4: 42186 | E4: Closed | F4: OFFLINE | G4: บริการรับชำระ | M4: 0 | N4: 0 | O4: 0 | P4: 100000 | T4: YES | U4: #N/A | V4: =VLOOKUP(A4,'2023 Stats'!$B$2:$D$192,3,FALSE) -> #N/A | W4: #N/A | Y4: #N/A | Z4: #N/A | AB4: #N/A | AE4: #N/A
A5: 1819 | B5: เงินฝากสมาชิกตราไปรษณียากร | C5: 42186 | E5: Open | F5: OFFLINE | G5: บริการรับชำระ | H5: Postal service | M5: 0 | N5: 1 | O5: 50000 | P5: 100000 | T5: YES | U5: 31/12/2023 | V5: =VLOOKUP(A5,'2023 Stats'!$B$2:$D$192,3,FALSE) -> 4383 | W5: 1096 | Y5: 4211 | Z5: 351 | AB5: #N/A | AE5: 723 | AH5: YES
A6: 10014 | B6: ส่งเงินเวสเทิร์นยูเนี่ยน/สอบถามค่าบริการ | C6: 42186 | E6: Open | F6: ONLINE | G6: บริการรับชำระ | I6: Western Union not to be done in Agency | L6: WU | M6: 0 | N6: 0 | O6: 0 | P6: 100000 | T6: YES | V6: =VLOOKUP(A6,'2023 Stats'!$B$2:$D$192,3,FALSE) -> #N/A | W6: #N/A | Y6: #N/A | Z6: #N/A | AB6: #N/A | AE6: #N/A
A7: 10015 | B7: จ่ายเงินเวสเทิร์นยูเนี่ยน | C7: 42186 | E7: Open | F7: ONLINE | G7: บริการรับชำระ | I7: Western Union not to be done in Agency | L7: WU | M7: 0 | N7: 0 | O7: 0 | P7: 100000 | T7: YES | V7: =VLOOKUP(A7,'2023 Stats'!$B$2:$D$192,3,FALSE) -> #N/A | W7: #N/A | Y7: #N/A | Z7: #N/A | AB7: #N/A | AE7: #N/A | AH7: YES
A8: 10016 | B8: ตรวจสอบสถานะจ่ายเงิน เวสเทิร์นยูเนี่ยน | C8: 42005 | E8: Open | F8: ONLINE | G8: บริการรับชำระ | I8: Western Union not to be done in Agency | L8: WU | M8: 0 | N8: 0 | O8: 0 | P8: 100000 | T8: YES | V8: =VLOOKUP(A8,'2023 Stats'!$B$2:$D$192,3,FALSE) -> #N/A | W8: #N/A | Y8: #N/A | Z8: #N/A | AB8: #N/A | AE8: #N/A | AI8: Inquiry
A9: 10017 | B9: สอบถามค่าบริการ | C9: 42005 | E9: Open | F9: ONLINE | G9: บริการรับชำระ | I9: Western Union not to be done in Agency | L9: WU | M9: 0 | N9: 0 | O9: 0 | P9: 100000 | T9: YES | V9: =VLOOKUP(A9,'2023 Stats'!$B$2:$D$192,3,FALSE) -> #N/A | W9: #N/A | Y9: #N/A | Z9: #N/A | AB9: #N/A | AE9: #N/A | AI9: Inquiry
A10: 10018 | B10: F2ZOOM | C10: 42005 | E10: Open | F10: ONLINE | G10: บริการรับชำระ | I10: Western Union not to be done in Agency | L10: WU | M10: 0 | N10: 0 | O10: 0 | P10: 100000 | T10: YES | V10: =VLOOKUP(A10,'2023 Stats'!$B$2:$D$192,3,FALSE) -> #N/A | W10: #N/A | Y10: #N/A | Z10: #N/A | AB10: #N/A | AE10: #N/A | AI10: Inquiry
A11: 10020 | B11: ลงทะเบียนกล่องดิจิตอล | C11: 42736 | E11: Closed | F11: OFFLINE | G11: บริการรับชำระ | M11: 0 | N11: 1 | O11: 0 | P11: 100000 | T11: YES | U11: #N/A | V11: =VLOOKUP(A11,'2023 Stats'!$B$2:$D$192,3,FALSE) -> #N/A | W11: #N/A | Y11: #N/A | Z11: #N/A | AB11: #N/A | AE11: #N/A | AI11: ปิดใช้บริการ
A12: 10021 | B12: ตรวจสอบลายมือชื่อผู้มีสิทธิ์สั่งจ่าย | C12: 42736 | E12: Closed | F12: OFFLINE/iFrame | G12: บริการรับชำระ | M12: 0 | N12: 1 | O12: 0 | P12: 100000 | T12: YES | U12: #N/A | V12: =VLOOKUP(A12,'2023 Stats'!$B$2:$D$192,3,FALSE) -> #N/A | W12: #N/A | Y12: #N/A | Z12: #N/A | AB12: #N/A | AE12: #N/A
A13: 10022 | B13: Drop-off | C13: 43344 | E13: Closed | F13: OFFLINE/iFrame | G13: บริการรับชำระ | H13: Postal service | M13: 0 | N13: 1 | O13: 0 | P13: 100000 | T13: YES | U13: #N/A | V13: =VLOOKUP(A13,'2023 Stats'!$B$2:$D$192,3,FALSE) -> #N/A | W13: #N/A | Y13: #N/A | Z13: #N/A | AB13: #N/A | AE13: #N/A | AI13: สอบถามเฉยๆ
A14: 10023 | B14: ตรวจสอบ Wallet@Post | C14: 43101 | E14: Open | F14: OFFLINE/iFrame | G14: บริการรับชำระ | H14: Check Wallet@post | M14: 0 | N14: 0 | O14: 0 | P14: 100000 | T14: YES | V14: =VLOOKUP(A14,'2023 Stats'!$B$2:$D$192,3,FALSE) -> #N/A | W14: #N/A | Y14: #N/A | Z14: #N/A | AB14: #N/A | AE14: #N/A | AI14: Inquiry
A15: 10025 | B15: ตรวจสอบรายชื่อบุคคลที่ห้ามทำธุรกรรม | C15: 43983 | E15: Closed | F15: OFFLINE/iFrame | G15: บริการรับชำระ | H15: Service payment | M15: 0 | N15: 0 | O15: 0 | P15: 100000 | T15: YES | U15: #N/A | V15: =VLOOKUP(A15,'2023 Stats'!$B$2:$D$192,3,FALSE) -> #N/A | W15: #N/A | Y15: #N/A | Z15: #N/A | AB15: #N/A | AE15: #N/A | AI15: สอบถามเฉยๆ
A16: 10050 | B16: Pay@WU Order Payment | C16: 43733 | E16: Open | F16: ONLINE | G16: บริการรับชำระ | I16: Not to be offered via Agency | L16: WU | M16: 0 | N16: 1 | O16: 50000 | P16: 100000 | T16: YES | U16: 31/12/2023 | V16: =VLOOKUP(A16,'2023 Stats'!$B$2:$D$192,3,FALSE) -> #N/A | W16: #N/A | Y16: 23 | Z16: 2 | AB16: #N/A | AE16: #N/A
A17: 10051 | B17: Pay@WU Order Refund | C17: 43733 | E17: Open | F17: ONLINE | G17: บริการรับชำระ | I17: Not to be offered via Agency | L17: WU | M17: 0 | N17: 1 | O17: 50000 | P17: 100000 | T17: YES | U17: 31/12/2023 | V17: =VLOOKUP(A17,'2023 Stats'!$B$2:$D$192,3,FALSE) -> #N/A | W17: #N/A | Y17: 23 | Z17: 2 | AB17: #N/A | AE17: #N/A | AH17: YES
A18: 20000 | B18: Fix Form Search | C18: 42186 | E18: Closed | F18: OFFLINE | G18: บริการรับชำระ | M18: 0 | N18: 0 | O18: 0 | P18: 100000 | T18: YES | U18: #N/A | V18: =VLOOKUP(A18,'2023 Stats'!$B$2:$D$192,3,FALSE) -> #N/A | W18: #N/A | Y18: #N/A | Z18: #N/A | AB18: #N/A | AE18: #N/A
A19: 30078 | B19: รับชำระค่าสินค้าเรียกเก็บเงินที่บ้าน - DPost | C19: 42182 | E19: Open | F19: ONLINE | G19: บริการรับชำระ | H19: Dpost payment | I19: Special Case | J19: No Barcode | K19: 10 | L19: บท. | M19: 0 | N19: 1 | O19: 50000 | P19: 100000 | T19: YES | U19: 31/12/2023 | V19: =VLOOKUP(A19,'2023 Stats'!$B$2:$D$192,3,FALSE) -> #N/A | W19: #N/A | X19: 1 | Y19: 22574347 | Z19: 1881196 | AA19: 1 | AB19: #N/A | AE19: #N/A | AF19: 1 | AH19: YES
A20: 30079 | B20: รับชำระค่าสินค้าเรียกเก็บเงินที่บ้าน (TND) | C20: 44227 | E20: Open | F20: ONLINE | G20: บริการรับชำระ | H20: Dpost payment | L20: บท. | M20: 0 | N20: 1 | O20: 50000 | P20: 100000 | T20: YES | U20: 31/12/2023 | V20: =VLOOKUP(A20,'2023 Stats'!$B$2:$D$192,3,FALSE) -> #N/A | W20: #N/A | Y20: #N/A | Z20: #N/A | AB20: #N/A | AE20: #N/A | AH20: YES
A21: 30156 | B21: บริการรับชำระบัตรเครดิตยูโอบี (Online) | C21: 42186 | D21: 15/09/2025 | E21: Closed | F21: ONLINE | G21: บริการรับชำระ | H21: Banking | I21: Credit Card Flow | J21: Standard | K21: 3 | L21: UOB | M21: 0 | N21: 1 | O21: 50000 | P21: 100000 | T21: YES | U21: 31/12/2023 | V21: =VLOOKUP(A21,'2023 Stats'!$B$2:$D$192,3,FALSE) -> 19952 | W21: 4988 | Y21: 27913 | Z21: 2326 | AB21: #N/A | AE21: 3657
A22: 30221 | B22: เงินฝากสมาชิกสิ่งสะสม | C22: 42186 | E22: Open | F22: OFFLINE | G22: บริการรับชำระ | H22: Postal service | M22: 0 | N22: 1 | O22: 50000 | P22: 100000 | S22: O7 | T22: YES | U22: 31/12/2023 | V22: =VLOOKUP(A22,'2023 Stats'!$B$2:$D$192,3,FALSE) -> 589 | W22: 147 | Y22: 589 | Z22: 49 | AB22: #N/A | AE22: 98 | AH22: YES
A23: 50002 | B23: ค่าน้ำประปานครหลวง | C23: 42186 | E23: Open | F23: OFFLINE | G23: บริการตัวการตัวแทน | H23: Utilities | M23: 10 | N23: 1 | O23: 50000 | P23: 100000 | Q23: YES | R23: YES | S23: O7 | T23: YES | U23: 31/12/2023 | V23: =VLOOKUP(A23,'2023 Stats'!$B$2:$D$192,3,FALSE) -> 3720 | W23: 930 | Y23: 4900 | Z23: 408 | AB23: 7621 | AC23: 635 | AE23: 658
A24: 50082 | B24: สินค้าเชื่อ/งวดเงินกู้/บัตรเครดิต AEON | C24: 42186 | D24: 44556 | E24: Closed | F24: OFFLINE | G24: บริการรับชำระ | M24: 0 | N24: 1 | O24: 50000 | P24: 100000 | T24: YES | U24: 44555 | V24: =VLOOKUP(A24,'2023 Stats'!$B$2:$D$192,3,FALSE) -> #N/A | W24: #N/A | Y24: #N/A | Z24: #N/A | AB24: 6055 | AC24: 505 | AE24: #N/A
A25: 50099 | B25: ค่าโทรศัพท์ | C25: 42186 | D25: 42886 | E25: Closed | F25: OFFLINE | G25: บริการตัวการตัวแทน | M25: 0 | N25: 0 | O25: 0 | P25: 100000 | T25: YES | U25: #N/A | V25: =VLOOKUP(A25,'2023 Stats'!$B$2:$D$192,3,FALSE) -> #N/A | W25: #N/A | Y25: #N/A | Z25: #N/A | AB25: #N/A | AE25: #N/A
A26: 50113 | B26: GE ค่า First Choice | C26: 42186 | E26: Open | F26: OFFLINE | G26: บริการรับชำระ | H26: Service payment | I26: Manual input | K26: 4 | M26: 10 | N26: 1 | O26: 50000 | P26: 100000 | T26: YES | U26: 31/12/2023 | V26: =VLOOKUP(A26,'2023 Stats'!$B$2:$D$192,3,FALSE) -> 4185 | W26: 1046 | Y26: 5903 | Z26: 492 | AB26: 10481 | AC26: 873 | AE26: 804
A27: 50115 | B27: GE Power Buy | C27: 42186 | D27: 42886 | E27: Closed | F27: OFFLINE | G27: บริการรับชำระ | M27: 0 | N27: 1 | O27: 50000 | P27: 100000 | T27: YES | U27: #N/A | V27: =VLOOKUP(A27,'2023 Stats'!$B$2:$D$192,3,FALSE) -> #N/A | W27: #N/A | Y27: #N/A | Z27: #N/A | AB27: #N/A | AE27: #N/A
A28: 50116 | B28: GE Central Card | C28: 42186 | E28: Open | F28: OFFLINE | G28: บริการรับชำระ | H28: Service payment | M28: 10 | N28: 1 | O28: 50000 | P28: 100000 | T28: YES | V28: =VLOOKUP(A28,'2023 Stats'!$B$2:$D$192,3,FALSE) -> #N/A | W28: #N/A | Y28: #N/A | Z28: #N/A | AB28: 4 | AC28: 0 | AE28: #N/A
A29: 50117 | B29: ชำระค่างวด AYUDHYA Capital Auto Lease | C29: 42186 | D29: 31/03/2026 | E29: Closed | F29: OFFLINE | G29: บริการรับชำระ | H29: Loan | I29: Scan Bill Only | J29: Standard | K29: 5 | M29: 10 | N29: 1 | O29: 50000 | P29: 100000 | T29: YES | U29: 31/12/2023 | V29: =VLOOKUP(A29,'2023 Stats'!$B$2:$D$192,3,FALSE) -> 4558 | W29: 1140 | Y29: 5863 | Z29: 489 | AB29: 8736 | AC29: 728 | AE29: 785
A30: 50118 | B30: TESCO LOTUS CARD | C30: 42186 | E30: Open | F30: OFFLINE | G30: บริการรับชำระ | H30: Service payment | M30: 10 | N30: 1 | O30: 50000 | P30: 100000 | T30: YES | V30: =VLOOKUP(A30,'2023 Stats'!$B$2:$D$192,3,FALSE) -> #N/A | W30: #N/A | Y30: #N/A | Z30: #N/A | AB30: #N/A | AE30: #N/A
A31: 50122 | B31: GE ค่า Quick Cash บ.โลตัสส์ มันนี่ เซอร์วิสเซส | C31: 42186 | E31: Open | F31: OFFLINE | G31: บริการรับชำระ | H31: Service payment | M31: 10 | N31: 1 | O31: 50000 | P31: 100000 | T31: YES | V31: =VLOOKUP(A31,'2023 Stats'!$B$2:$D$192,3,FALSE) -> 2 | W31: 1 | Y31: #N/A | Z31: #N/A | AB31: 4 | AC31: 0 | AE31: #N/A
A32: 50126 | B32: ชำระภาษีเงินได้ ภงด. | C32: 42186 | E32: Open | F32: OFFLINE | G32: บริการรับชำระ | H32: Service payment | I32: Special Case | J32: No Barcode | K32: 5 | M32: 10 | N32: 1 | O32: 50000 | P32: 100000 | T32: YES | U32: 31/12/2023 | V32: =VLOOKUP(A32,'2023 Stats'!$B$2:$D$192,3,FALSE) -> 19927 | W32: 4982 | Y32: 19122 | Z32: 1594 | AB32: 25347 | AC32: 2112 | AE32: 2896
A33: 50127 | B33: GE HomePro | C33: 42186 | E33: Open | F33: OFFLINE | G33: บริการรับชำระ | H33: Service payment | M33: 0 | N33: 1 | O33: 50000 | P33: 100000 | T33: YES | V33: =VLOOKUP(A33,'2023 Stats'!$B$2:$D$192,3,FALSE) -> #N/A | W33: #N/A | Y33: #N/A | Z33: #N/A | AB33: #N/A | AE33: #N/A
A34: 50131 | B34: ชำระค่าเบี้ยประกัน บ.ฟิลลิปฯ | C34: 42186 | E34: Open | F34: OFFLINE | G34: บริการรับชำระ | H34: Insurance | M34: 0 | N34: 1 | O34: 50000 | P34: 100000 | T34: YES | U34: 31/12/2023 | V34: =VLOOKUP(A34,'2023 Stats'!$B$2:$D$192,3,FALSE) -> 364 | W34: 91 | Y34: 467 | Z34: 39 | AB34: 790 | AC34: 66 | AE34: 65
A35: 50166 | B35: สมัครใหม่/ค่าธรรมเนียม/สัมฤทธิ์ ป.ตรี มสธ. | C35: 42186 | E35: Open | F35: OFFLINE | G35: บริการรับชำระ | H35: University Service | I35: Special Case | J35: Custom | K35: 9 | M35: 10 | N35: 1 | O35: 50000 | P35: 100000 | T35: YES | U35: 31/12/2023 | V35: =VLOOKUP(A35,'2023 Stats'!$B$2:$D$192,3,FALSE) -> 6145 | W35: 1536 | Y35: 10377 | Z35: 865 | AB35: 14353 | AC35: 1196 | AE35: 1199
A36: 50168 | B36: บัตรเครดิต ธ.ไทยพาณิชย์ | C36: 42186 | E36: Closed | F36: OFFLINE | G36: บริการรับชำระ | H36: Banking | M36: 10 | N36: 1 | O36: 50000 | P36: 100000 | T36: YES | U36: 31/12/2023 | V36: =VLOOKUP(A36,'2023 Stats'!$B$2:$D$192,3,FALSE) -> 3002 | W36: 751 | Y36: 4860 | Z36: 405 | AB36: 7598 | AC36: 633 | AE36: 596
A37: 50205 | B37: ชำระเงินสินค้า ออริเฟลม คอสเมติกส์ | C37: 42186 | D37: 25/10,2018 | E37: Closed | F37: OFFLINE | G37: บริการรับชำระ | M37: 0 | N37: 0 | O37: 0 | P37: 100000 | T37: YES | U37: #N/A | V37: =VLOOKUP(A37,'2023 Stats'!$B$2:$D$192,3,FALSE) -> #N/A | W37: #N/A | Y37: #N/A | Z37: #N/A | AB37: #N/A | AE37: #N/A
A38: 50207 | B38: ชำระค่างวด ค่าเบี้ยฯ ค่าต่อทะเบียนรถ | C38: 42186 | E38: Closed | F38: OFFLINE | G38: บริการรับชำระ | H38: Service payment | M38: 0 | N38: 1 | O38: 50000 | P38: 100000 | T38: YES | U38: #N/A | V38: =VLOOKUP(A38,'2023 Stats'!$B$2:$D$192,3,FALSE) -> #N/A | W38: #N/A | Y38: #N/A | Z38: #N/A | AB38: #N/A | AE38: #N/A
A39: 50233 | B39: ชำระเบี้ยประกันไทยประกันชีวิต (Online) | C39: 42186 | E39: Open | F39: ONLINE | G39: บริการรับชำระ | H39: Insurance | I39: Credit Card Flow | J39: Standard | K39: 8 | L39: Thailife | M39: 0 | N39: 1 | O39: 50000 | P39: 100000 | T39: YES | U39: 31/12/2023 | V39: =VLOOKUP(50233,'2023 Stats'!$B$2:$D$192,3,FALSE)+VLOOKUP(51081,'2023 Stats'!$B$2:$D$192,3,FALSE) -> 5821 | W39: 1426 | Y39: 6968 | Z39: 581 | AB39: 8310 | AC39: 693 | AE39: 900
A40: 50235 | B40: ชำระค่า พกง. เบล เมซอง | C40: 42186 | E40: Closed | F40: OFFLINE | G40: บริการรับชำระ | H40: Service payment | M40: 0 | N40: 0 | O40: 0 | P40: 100000 | T40: YES | U40: #N/A | V40: =VLOOKUP(A40,'2023 Stats'!$B$2:$D$192,3,FALSE) -> #N/A | W40: #N/A | Y40: #N/A | Z40: #N/A | AB40: #N/A | AE40: #N/A
A41: 50259 | B41: ชำระค่าเบี้ยประกันกรุงเทพประกันชีวิต | C41: 42186 | E41: Open | F41: OFFLINE | G41: บริการรับชำระ | H41: Insurance | M41: 0 | N41: 1 | O41: 50000 | P41: 100000 | T41: YES | U41: 31/12/2023 | V41: =VLOOKUP(A41,'2023 Stats'!$B$2:$D$192,3,FALSE) -> 1 | W41: 0 | Y41: 5 | Z41: 0 | AB41: 16 | AC41: 1 | AE41: 1
A42: 50264 | B42: ชำระเงินค่าเช่าซื้อ บริษัท กรุ๊ปลีส | C42: 42186 | E42: Open | F42: OFFLINE | G42: บริการรับชำระ | H42: Service payment | M42: 10 | N42: 1 | O42: 50000 | P42: 100000 | T42: YES | U42: 31/12/2023 | V42: =VLOOKUP(A42,'2023 Stats'!$B$2:$D$192,3,FALSE) -> 160 | W42: 40 | Y42: 256 | Z42: 21 | AB42: 497 | AC42: 41 | AE42: 34
A43: 50280 | B43: เซ็นทรัลเพอร์ซันนัลโลน (Central PLoan) | C43: 42186 | E43: Open | F43: OFFLINE | G43: บริการรับชำระ | H43: Loan | M43: 10 | N43: 1 | O43: 50000 | P43: 100000 | T43: YES | U43: 31/12/2023 | V43: =VLOOKUP(A43,'2023 Stats'!$B$2:$D$192,3,FALSE) -> 9 | W43: 2 | Y43: 429 | Z43: 36 | AB43: 125 | AC43: 10 | AE43: 16
A44: 50293 | B44: ชำระสินเชื่อเงินสด TESCO PERSONAL LOAN | C44: 42186 | E44: Open | F44: OFFLINE | G44: บริการรับชำระ | H44: Loan | M44: 10 | N44: 1 | O44: 50000 | P44: 100000 | T44: YES | V44: =VLOOKUP(A44,'2023 Stats'!$B$2:$D$192,3,FALSE) -> #N/A | W44: #N/A | Y44: #N/A | Z44: #N/A | AB44: #N/A | AE44: #N/A
A45: 50295 | B45: ชำระเงินกู้ธนาคาร SME BANK | C45: 42186 | E45: Open | F45: OFFLINE | G45: บริการรับชำระ | H45: Banking | I45: Scan Bill Only | J45: Standard | K45: 7 | M45: 10 | N45: 1 | O45: 50000 | P45: 100000 | T45: YES | U45: 31/12/2023 | V45: =VLOOKUP(A45,'2023 Stats'!$B$2:$D$192,3,FALSE) -> 4202 | W45: 1051 | Y45: 5864 | Z45: 489 | AB45: 8099 | AC45: 675 | AE45: 738
A46: 50297 | B46: ชำระค่าเบี้ยประกัน กรุงเทพประกันภัย | C46: 42186 | E46: Open | F46: OFFLINE | G46: บริการรับชำระ | H46: Insurance | M46: 0 | N46: 1 | O46: 50000 | P46: 100000 | T46: YES | U46: 31/12/2023 | V46: =VLOOKUP(A46,'2023 Stats'!$B$2:$D$192,3,FALSE) -> 429 | W46: 107 | Y46: 508 | Z46: 42 | AB46: 742 | AC46: 62 | AE46: 70
A47: 50308 | B47: ชำระค่าหุ้น ค่างวด สหกรณ์ออมทรัพย์ กสท. | C47: 42186 | E47: Open | F47: OFFLINE | G47: บริการรับชำระ | H47: Mutual fund | I47: Scan Bill + Manual Input | J47: Standard | K47: 8 | M47: 0 | N47: 1 | O47: 50000 | P47: 100000 | T47: YES | U47: 31/12/2023 | V47: =VLOOKUP(A47,'2023 Stats'!$B$2:$D$192,3,FALSE) -> 7829 | W47: 1957 | Y47: 10873 | Z47: 906 | AB47: 12666 | AC47: 1056 | AE47: 1306
A48: 50311 | B48: ชำระค่าสินค้า บริษัท ดีเคเอสเอช จำกัด | C48: 42186 | D48: 43145 | E48: Closed | F48: OFFLINE | G48: บริการรับชำระ | M48: 0 | N48: 1 | O48: 50000 | P48: 100000 | T48: YES | U48: #N/A | V48: =VLOOKUP(A48,'2023 Stats'!$B$2:$D$192,3,FALSE) -> #N/A | W48: #N/A | Y48: #N/A | Z48: #N/A | AB48: #N/A | AE48: #N/A
A49: 50313 | B49: บริษัท ซิงเกอร์ประเทศไทย จำกัด (มหาชน) | C49: 42186 | E49: Closed | F49: OFFLINE | G49: บริการรับชำระ | H49: Goods payment | M49: 10 | N49: 1 | O49: 50000 | P49: 100000 | T49: YES | U49: 30/06/2022 | V49: =VLOOKUP(A49,'2023 Stats'!$B$2:$D$192,3,FALSE) -> #N/A | W49: #N/A | Y49: 3 | Z49: 0 | AB49: 4 | AC49: 0 | AE49: #N/A
A50: 50314 | B50: ค่าธรรมเนียมพรบ.ควบคุมน้ำมันเชื้อเพลิง 42 | C50: 42186 | E50: Open | F50: OFFLINE | G50: บริการรับชำระ | H50: Service payment | M50: 30 | N50: 1 | O50: 50000 | P50: 100000 | T50: YES | U50: 31/12/2023 | V50: =VLOOKUP(A50,'2023 Stats'!$B$2:$D$192,3,FALSE) -> 1646 | W50: 412 | Y50: 1698 | Z50: 142 | AB50: 3345 | AC50: 279 | AE50: 277
A51: 50315 | B51: ค่าธรรมเนียมพรบ.การค้าน้ำมันเชื้อเพลิง43 | C51: 42186 | E51: Closed | F51: OFFLINE | G51: บริการรับชำระ | H51: Service payment | M51: 30 | N51: 0 | O51: 0 | P51: 100000 | T51: YES | U51: 31/12/2023 | V51: =VLOOKUP(A51,'2023 Stats'!$B$2:$D$192,3,FALSE) -> 59 | W51: 15 | Y51: 62 | Z51: 5 | AB51: 225 | AC51: 19 | AE51: 13
A52: 50316 | B52: ค่าธรรมเนียม ประกาศคณะปฏิวัติ ปว.28 | C52: 42186 | E52: Open | F52: OFFLINE | G52: บริการรับชำระ | H52: Service payment | M52: 30 | N52: 1 | O52: 50000 | P52: 100000 | T52: YES | U52: 31/12/2023 | V52: =VLOOKUP(A52,'2023 Stats'!$B$2:$D$192,3,FALSE) -> 591 | W52: 148 | Y52: 439 | Z52: 37 | AB52: 1582 | AC52: 132 | AE52: 105
A53: 50325 | B53: ชำระค่า พกง. บริษัท วีน จำกัด | C53: 42186 | E53: Closed | F53: OFFLINE | G53: บริการรับชำระ | H53: Goods payment | M53: 0 | N53: 0 | O53: 0 | P53: 100000 | T53: YES | U53: #N/A | V53: =VLOOKUP(A53,'2023 Stats'!$B$2:$D$192,3,FALSE) -> #N/A | W53: #N/A | Y53: #N/A | Z53: #N/A | AB53: #N/A | AE53: #N/A
A54: 50328 | B54: เปลี่ยนสาขา,ที่อยู่,ชื่อ_สกุล,ทำบัตร นศ. มสธ. | C54: 42186 | E54: Open | F54: OFFLINE | G54: บริการรับชำระ | H54: University Service | M54: 10 | N54: 1 | O54: 50000 | P54: 100000 | T54: YES | U54: 31/12/2023 | V54: =VLOOKUP(A54,'2023 Stats'!$B$2:$D$192,3,FALSE) -> 2680 | W54: 670 | Y54: 3933 | Z54: 328 | AB54: 3419 | AC54: 285 | AE54: 428
A55: 50329 | B55: ลงทะเบียนชุดวิชา ม.สุโขทัยธรรมาธิราช | C55: 42186 | E55: Open | F55: OFFLINE | G55: บริการรับชำระ | H55: University Service | I55: Special Case | J55: No Barcode | K55: 14 | M55: 10 | N55: 1 | O55: 50000 | P55: 100000 | T55: YES | U55: 31/12/2023 | V55: =VLOOKUP(A55,'2023 Stats'!$B$2:$D$192,3,FALSE) -> 21710 | W55: 5428 | Y55: 38695 | Z55: 3225 | AB55: 31607 | AC55: 2634 | AE55: 3762
A56: 50348 | B56: ชำระค่าบัตรเครดิต TESCO VISA CARD | C56: 42186 | E56: Open | F56: OFFLINE | G56: บริการรับชำระ | H56: Banking | M56: 10 | N56: 1 | O56: 50000 | P56: 100000 | T56: YES | U56: 31/12/2023 | V56: =VLOOKUP(A56,'2023 Stats'!$B$2:$D$192,3,FALSE) -> 949 | W56: 237 | Y56: 1357 | Z56: 113 | AB56: 2678 | AC56: 223 | AE56: 191
A57: 50355 | B57: ค่าน้ำประปาส่วนภูมิภาค (Barcode 1 แถว) | C57: 42186 | E57: Closed | F57: OFFLINE | G57: บริการตัวการตัวแทน | M57: 0 | N57: 0 | O57: 0 | P57: 100000 | T57: YES | U57: #N/A | V57: =VLOOKUP(A57,'2023 Stats'!$B$2:$D$192,3,FALSE) -> #N/A | W57: #N/A | Y57: #N/A | Z57: #N/A | AB57: #N/A | AE57: #N/A
A58: 50356 | B58: ค่าน้ำประปาส่วนภูมิภาค (ไม่มี Barcode) | C58: 42186 | E58: Closed | F58: OFFLINE | G58: บริการตัวการตัวแทน | M58: 0 | N58: 0 | O58: 0 | P58: 100000 | T58: YES | U58: #N/A | V58: =VLOOKUP(A58,'2023 Stats'!$B$2:$D$192,3,FALSE) -> #N/A | W58: #N/A | Y58: #N/A | Z58: #N/A | AB58: #N/A | AE58: #N/A
A59: 50357 | B59: ค่าธรรมเนียมค้าน้ำมันเชื้อเพลิง43รายใหม่ | C59: 42186 | E59: Closed | F59: OFFLINE | G59: บริการรับชำระ | H59: Service payment | M59: 30 | N59: 0 | O59: 0 | P59: 100000 | T59: YES | U59: 31/12/2023 | V59: =VLOOKUP(A59,'2023 Stats'!$B$2:$D$192,3,FALSE) -> 18 | W59: 5 | Y59: 1 | Z59: 0 | AB59: 20 | AC59: 2 | AE59: 2
A60: 50366 | B60: ค่าโทรศัพท์เคลื่อนที่(GSM1800) (ใหม่) | C60: 42186 | E60: Closed | F60: OFFLINE | G60: บริการรับชำระ | M60: 0 | N60: 0 | O60: 0 | P60: 100000 | T60: YES | U60: #N/A | V60: =VLOOKUP(A60,'2023 Stats'!$B$2:$D$192,3,FALSE) -> #N/A | W60: #N/A | Y60: #N/A | Z60: #N/A | AB60: #N/A | AE60: #N/A
A61: 50370 | B61: ค่าเบี้ยประกันเจนเนอราลี่ประกัน(ใหม่) | C61: 42186 | D61: 44909 | E61: Closed | F61: OFFLINE | G61: บริการรับชำระ | M61: 0 | N61: 1 | O61: 50000 | P61: 100000 | T61: YES | U61: 44895 | V61: =VLOOKUP(A61,'2023 Stats'!$B$2:$D$192,3,FALSE) -> #N/A | W61: #N/A | Y61: 35 | Z61: 3 | AB61: 38 | AC61: 3 | AE61: #N/A
A62: 50376 | B62: ค่าโทรศัพท์ TOT ใหม่ | C62: 42186 | E62: Closed | F62: OFFLINE | G62: บริการตัวการตัวแทน | H62: Utilities | I62: Scan Bill + Manual Input | J62: Standard | K62: 12 | M62: 10 | N62: 0 | O62: 0 | P62: 100000 | Q62: YES | R62: YES | T62: YES | U62: 31/12/2023 | V62: =VLOOKUP(A62,'2023 Stats'!$B$2:$D$192,3,FALSE) -> 31772 | W62: 7943 | Y62: 52042 | Z62: 4337 | AB62: 78230 | AC62: 6519 | AD62: 7 | AE62: 6266
A63: 50386 | B63: เช่าซื้อสินค้า/เงินกู้/บัตรเครดิต(ใหม่) | C63: 42186 | D63: 44556 | E63: Closed | F63: OFFLINE | G63: บริการรับชำระ | M63: 0 | N63: 1 | O63: 50000 | P63: 100000 | T63: YES | U63: 44555 | V63: =VLOOKUP(A63,'2023 Stats'!$B$2:$D$192,3,FALSE) -> #N/A | W63: #N/A | Y63: #N/A | Z63: #N/A | AB63: 17317 | AC63: 1443 | AE63: #N/A
A64: 50386 | B64: เช่าซื้อสินค้า/เงินกู้/บัตรเครดิต(ใหม่) | C64: 42011 | E64: Closed | F64: OFFLINE | M64: 0 | N64: 0 | O64: 0 | P64: 100000 | Q64: 200-9,999 | V64: =VLOOKUP(A64,'2023 Stats'!$B$2:$D$192,3,FALSE) -> #N/A | Y64: 200-9,999 | AB64: 200-9,999 | AE64: 200-9,999
A65: 50387 | B65: ค่าบริการโทรคมฯ TBOSS กสท. (ใหม่) | C65: 42186 | E65: Open | F65: OFFLINE | G65: บริการตัวการตัวแทน | H65: Utilities | M65: 10 | N65: 1 | O65: 50000 | P65: 100000 | Q65: YES | R65: YES | S65: O7 | T65: YES | U65: 31/12/2023 | V65: =VLOOKUP(A65,'2023 Stats'!$B$2:$D$192,3,FALSE) -> 2206 | W65: 552 | Y65: 2247 | Z65: 187 | AB65: 3915 | AC65: 326 | AE65: 355
A66: 50395 | B66: ชำระค่าบัตรเครดิตกรุงศรีอยุธยา (DreamLoan) | C66: 42186 | E66: Open | F66: OFFLINE | G66: บริการรับชำระ | H66: Banking | M66: 10 | N66: 1 | O66: 50000 | P66: 100000 | T66: YES | U66: 31/12/2023 | V66: =VLOOKUP(A66,'2023 Stats'!$B$2:$D$192,3,FALSE) -> 89 | W66: 22 | Y66: 171 | Z66: 14 | AB66: 311 | AC66: 26 | AE66: 21
A67: 50403 | B67: ค่าสินค้าใหม่Mistine(Service codeBWC) | C67: 42186 | E67: Closed | F67: OFFLINE | G67: บริการรับชำระ | H67: Goods payment | M67: 0 | N67: 1 | O67: 50000 | P67: 100000 | T67: YES | U67: #N/A | V67: =VLOOKUP(A67,'2023 Stats'!$B$2:$D$192,3,FALSE) -> #N/A | W67: #N/A | Y67: #N/A | Z67: #N/A | AB67: #N/A | AE67: #N/A
A68: 50411 | B68: ค่าธรรมเนียมการสมัครสอบเข้าเป็นนิสิต | C68: 42186 | E68: Closed | F68: OFFLINE | G68: บริการรับชำระ | H68: Service payment | M68: 0 | N68: 0 | O68: 0 | P68: 100000 | T68: YES | U68: #N/A | V68: =VLOOKUP(A68,'2023 Stats'!$B$2:$D$192,3,FALSE) -> #N/A | W68: #N/A | Y68: #N/A | Z68: #N/A | AB68: #N/A | AE68: #N/A
A69: 50412 | B69: รับเงินฝาก สหกรณ์ออมทรัพย์ กสท. | C69: 42186 | E69: Open | F69: OFFLINE | G69: บริการรับชำระ | H69: Mutual fund | M69: 10,15 | N69: 1 | O69: 50000 | P69: 100000 | T69: YES | U69: 31/12/2023 | V69: =VLOOKUP(A69,'2023 Stats'!$B$2:$D$192,3,FALSE) -> 131 | W69: 33 | Y69: 90 | Z69: 8 | AB69: 138 | AC69: 12 | AE69: 17
A70: 50413 | B70: ชำระหนี้ก่อนกำหนด สหกรณ์ออมทรัพย์ กสท. | C70: 42186 | E70: Open | F70: OFFLINE | G70: บริการรับชำระ | H70: Mutual fund | M70: 10,15 | N70: 1 | O70: 50000 | P70: 100000 | T70: YES | U70: 31/12/2023 | V70: =VLOOKUP(A70,'2023 Stats'!$B$2:$D$192,3,FALSE) -> 117 | W70: 29 | Y70: 93 | Z70: 8 | AB70: 199 | AC70: 17 | AE70: 18
A71: 50416 | B71: ชำระค่าสินเชื่อ Revoling Credit | C71: 42186 | E71: Closed | F71: OFFLINE | G71: บริการรับชำระ | H71: Loan | M71: 0 | N71: 1 | O71: 50000 | P71: 100000 | T71: YES | U71: #N/A | V71: =VLOOKUP(A71,'2023 Stats'!$B$2:$D$192,3,FALSE) -> #N/A | W71: #N/A | Y71: #N/A | Z71: #N/A | AB71: #N/A | AE71: #N/A
A72: 50418 | B72: ชำระค่าสินค้า บริษัท ซิลลิค ฟาร์มา | C72: 42186 | E72: Open | F72: OFFLINE | G72: บริการรับชำระ | H72: Goods payment | M72: 0 | N72: 1 | O72: 50000 | P72: 100000 | T72: YES | U72: 31/12/2023 | V72: =VLOOKUP(A72,'2023 Stats'!$B$2:$D$192,3,FALSE) -> 546 | W72: 137 | Y72: 538 | Z72: 45 | AB72: 736 | AC72: 61 | AE72: 81
A73: 50419 | B73: เซ็นทรัลมาสเตอร์คาร์ด (MasterCard) | C73: 42186 | E73: Open | F73: OFFLINE | G73: บริการรับชำระ | H73: Banking | M73: 10 | N73: 1 | O73: 50000 | P73: 100000 | T73: YES | U73: 31/12/2023 | V73: =VLOOKUP(A73,'2023 Stats'!$B$2:$D$192,3,FALSE) -> 1203 | W73: 301 | Y73: 1666 | Z73: 139 | AB73: 2890 | AC73: 241 | AE73: 227
A74: 50420 | B74: ชำระค่าบัตรเครดิตกรุงศรีอยุธยา | C74: 42186 | E74: Open | F74: OFFLINE | G74: บริการรับชำระ | H74: Banking | M74: 10 | N74: 1 | O74: 50000 | P74: 100000 | T74: YES | U74: 31/12/2023 | V74: =VLOOKUP(A74,'2023 Stats'!$B$2:$D$192,3,FALSE) -> 2767 | W74: 692 | Y74: 4115 | Z74: 343 | AB74: 7088 | AC74: 591 | AE74: 542
A75: 50437 | B75: ชำระค่าสินค้า/บริการ สินทรัพย์สุขุมวิท | C75: 42186 | D75: 43312 | E75: Closed | F75: OFFLINE | G75: บริการรับชำระ | M75: 0 | N75: 0 | O75: 0 | P75: 100000 | T75: YES | U75: #N/A | V75: =VLOOKUP(A75,'2023 Stats'!$B$2:$D$192,3,FALSE) -> #N/A | W75: #N/A | Y75: #N/A | Z75: #N/A | AB75: #N/A | AE75: #N/A
A76: 50438 | B76: ชำระค่าบัตรเครดิต HSBC (ใหม่) | C76: 42186 | E76: Closed | F76: OFFLINE | G76: บริการรับชำระ | M76: 0 | N76: 1 | O76: 50000 | P76: 100000 | T76: YES | U76: #N/A | V76: =VLOOKUP(A76,'2023 Stats'!$B$2:$D$192,3,FALSE) -> #N/A | W76: #N/A | Y76: #N/A | Z76: #N/A | AB76: #N/A | AE76: #N/A
A77: 50458 | B77: ชำระค่าเบี้ยประกันภัย บ.บีทีประกันภัย | C77: 42186 | E77: Closed | F77: OFFLINE | G77: บริการรับชำระ | H77: Insurance | M77: 0 | N77: 1 | O77: 50000 | P77: 100000 | T77: YES | U77: #N/A | V77: =VLOOKUP(A77,'2023 Stats'!$B$2:$D$192,3,FALSE) -> #N/A | W77: #N/A | Y77: #N/A | Z77: #N/A | AB77: #N/A | AE77: #N/A
A78: 50460 | B78: ชำระค่างวดรถ บ.สกู๊ดเตอร์ อรีนา จำกัด | C78: 42186 | E78: Closed | F78: OFFLINE | G78: บริการรับชำระ | H78: Service payment | M78: 0 | N78: 1 | O78: 50000 | P78: 100000 | T78: YES | U78: #N/A | V78: =VLOOKUP(A78,'2023 Stats'!$B$2:$D$192,3,FALSE) -> #N/A | W78: #N/A | Y78: #N/A | Z78: #N/A | AB78: #N/A | AE78: #N/A
A79: 50462 | B79: ชำระสินเชื่อ CONSUMER PRO ไทยธนาคาร | C79: 42186 | E79: Open | F79: OFFLINE | G79: บริการรับชำระ | H79: Banking | M79: 10,15 | N79: 1 | O79: 50000 | P79: 100000 | T79: YES | U79: 31/12/2023 | V79: =VLOOKUP(A79,'2023 Stats'!$B$2:$D$192,3,FALSE) -> 331 | W79: 83 | Y79: 416 | Z79: 35 | AB79: 961 | AC79: 80 | AE79: 66
A80: 50465 | B80: ชำระเงินค่าสินเชื่อ&ค่าใช้จ่ายอื่น ธนชาต | C80: 42185 | D80: 44378 | E80: Closed | F80: OFFLINE | G80: บริการรับชำระ | M80: 0 | N80: 1 | O80: 50000 | P80: 100000 | T80: YES | U80: 44441 | V80: =VLOOKUP(A80,'2023 Stats'!$B$2:$D$192,3,FALSE) -> #N/A | W80: #N/A | Y80: #N/A | Z80: #N/A | AB80: 58344 | AC80: 4862 | AD80: 10 | AE80: #N/A
A81: 50466 | B81: ชำระเงินค่าสินเชื่อ&ค่าใช้จ่ายอื่น ธนชาต | C81: 42011 | E81: Closed | F81: OFFLINE | G81: บริการรับชำระ | M81: 0 | N81: 0 | O81: 0 | P81: 100000 | V81: =VLOOKUP(A81,'2023 Stats'!$B$2:$D$192,3,FALSE) -> #N/A
A82: 50471 | B82: โครงการสัมฤทธิบัตรบัณฑิตศึกษา | C82: 42186 | E82: Open | F82: OFFLINE | G82: บริการรับชำระ | H82: University Service | M82: 10 | N82: 1 | O82: 50000 | P82: 100000 | T82: YES | U82: 31/12/2023 | V82: =VLOOKUP(A82,'2023 Stats'!$B$2:$D$192,3,FALSE) -> 36 | W82: 9 | Y82: 20 | Z82: 2 | AB82: 34 | AC82: 3 | AE82: 5
A83: 50473 | B83: สมัครเข้าศึกษาระดับบัณฑิตศึกษา มสธ. | C83: 42186 | E83: Open | F83: OFFLINE | G83: บริการรับชำระ | H83: University Service | M83: 10 | N83: 1 | O83: 50000 | P83: 100000 | T83: YES | U83: 31/12/2023 | V83: =VLOOKUP(A83,'2023 Stats'!$B$2:$D$192,3,FALSE) -> 1599 | W83: 400 | Y83: 2821 | Z83: 235 | AB83: 3293 | AC83: 274 | AE83: 303
A84: 50474 | B84: คำร้องต่าง ๆ มสธ. (ป.โท-เอก) | C84: 42186 | E84: Open | F84: OFFLINE | G84: บริการรับชำระ | H84: University Service | M84: 10 | N84: 1 | O84: 50000 | P84: 100000 | T84: YES | U84: 31/12/2023 | V84: =VLOOKUP(A84,'2023 Stats'!$B$2:$D$192,3,FALSE) -> 705 | W84: 176 | Y84: 722 | Z84: 60 | AB84: 813 | AC84: 68 | AE84: 101
A85: 50475 | B85: ลงทะเบียนบัณฑิตศึกษา มสธ. (ป.โท) | C85: 42186 | E85: Open | F85: OFFLINE | G85: บริการรับชำระ | H85: University Service | M85: 10 | N85: 1 | O85: 50000 | P85: 100000 | T85: YES | U85: 31/12/2023 | V85: =VLOOKUP(A85,'2023 Stats'!$B$2:$D$192,3,FALSE) -> 916 | W85: 229 | Y85: 1456 | Z85: 121 | AB85: 2712 | AC85: 226 | AE85: 192
A86: 50476 | B86: ขึ้นทะเบียนมหาบัณฑิต บ.16 มสธ. (ป.โท-เอก) | C86: 42186 | E86: Open | F86: OFFLINE | G86: บริการรับชำระ | H86: University Service | M86: 10 | N86: 1 | O86: 50000 | P86: 100000 | T86: YES | U86: 31/12/2023 | V86: =VLOOKUP(A86,'2023 Stats'!$B$2:$D$192,3,FALSE) -> 789 | W86: 197 | Y86: 762 | Z86: 64 | AB86: 712 | AC86: 59 | AE86: 107
A87: 50477 | B87: ลงทะเบียนเรียน (กรณีชำระเงินเพิ่ม ป.โท) | C87: 42186 | E87: Open | F87: OFFLINE | G87: บริการรับชำระ | H87: University Service | M87: 10 | N87: 1 | O87: 50000 | P87: 100000 | T87: YES | U87: 31/12/2023 | V87: =VLOOKUP(A87,'2023 Stats'!$B$2:$D$192,3,FALSE) -> 4 | W87: 1 | Y87: 5 | Z87: 0 | AB87: 5 | AC87: 0 | AE87: 1
A88: 50478 | B88: ขึ้นทะเบียนบัณฑิตปริญญาตรี มสธ.16 | C88: 42186 | E88: Open | F88: OFFLINE | G88: บริการรับชำระ | H88: University Service | I88: Special Case | J88: Custom | K88: 6 | M88: 10 | N88: 1 | O88: 50000 | P88: 100000 | T88: YES | U88: 31/12/2023 | V88: =VLOOKUP(A88,'2023 Stats'!$B$2:$D$192,3,FALSE) -> 8890 | W88: 2223 | Y88: 10419 | Z88: 868 | AB88: 5950 | AC88: 496 | AE88: 1196
A89: 50479 | B89: ลงทะเบียนเรียน (กรณีชำระเงินเพิ่ม ป.ตรี) | C89: 42186 | E89: Open | F89: OFFLINE | G89: บริการรับชำระ | H89: University Service | M89: 10 | N89: 1 | O89: 50000 | P89: 100000 | T89: YES | U89: 31/12/2023 | V89: =VLOOKUP(A89,'2023 Stats'!$B$2:$D$192,3,FALSE) -> 240 | W89: 60 | Y89: 327 | Z89: 27 | AB89: 542 | AC89: 45 | AE89: 44
A90: 50480 | B90: ชำระค่าบริการ CS LOXINFO บาร์โค้ด 1 แถว | C90: 42186 | D90: 44634 | E90: Closed | F90: OFFLINE | G90: บริการรับชำระ | M90: 0 | N90: 0 | O90: 0 | P90: 100000 | T90: YES | U90: 44618 | V90: =VLOOKUP(A90,'2023 Stats'!$B$2:$D$192,3,FALSE) -> #N/A | W90: #N/A | Y90: 5 | Z90: 0 | AB90: 291 | AC90: 24 | AE90: #N/A
A91: 50489 | B91: ชำระค่างวดรถ โตโยต้า ลีสซิ่ง (กท-ตจว) | C91: 42186 | E91: Open | F91: OFFLINE | G91: บริการรับชำระ | H91: Loan | I91: Scan Bill + Manual Input | J91: Standard | K91: 7 | M91: 10,15 | N91: 1 | O91: 50000 | P91: 100000 | T91: YES | U91: 31/12/2023 | V91: =VLOOKUP(A91,'2023 Stats'!$B$2:$D$192,3,FALSE) -> 45466 | W91: 11367 | X91: 8 | Y91: 60249 | Z91: 5021 | AA91: 9 | AB91: 78649 | AC91: 6554 | AD91: 6 | AE91: 7647 | AF91: 8
A92: 50491 | B92: ใบรายงานผลฯ/หนังสือรับรอง บ10 ป.โท-เอก | C92: 42186 | E92: Open | F92: OFFLINE | G92: บริการรับชำระ | H92: University Service | M92: 10 | N92: 1 | O92: 50000 | P92: 100000 | T92: YES | U92: 31/12/2023 | V92: =VLOOKUP(A92,'2023 Stats'!$B$2:$D$192,3,FALSE) -> 1198 | W92: 300 | Y92: 1013 | Z92: 84 | AB92: 1144 | AC92: 95 | AE92: 160
A93: 50492 | B93: ขอหนังสือรับรอง/ใบรายงาน บ.29 (ป.โท) | C93: 42186 | E93: Open | F93: OFFLINE | G93: บริการรับชำระ | H93: University Service | M93: 10 | N93: 1 | O93: 50000 | P93: 100000 | T93: YES | U93: 31/12/2023 | V93: =VLOOKUP(A93,'2023 Stats'!$B$2:$D$192,3,FALSE) -> 145 | W93: 36 | Y93: 269 | Z93: 22 | AB93: 132 | AC93: 11 | AE93: 23
A94: 50505 | B94: ชำระค่างวด ตะวันออก ลีสซิ่ง | C94: 42186 | E94: Open | F94: OFFLINE | G94: บริการรับชำระ | H94: Loan | M94: 15,20 | N94: 1 | O94: 50000 | P94: 100000 | T94: YES | U94: 31/12/2023 | V94: =VLOOKUP(A94,'2023 Stats'!$B$2:$D$192,3,FALSE) -> 12 | W94: 3 | Y94: 24 | Z94: 2 | AB94: 93 | AC94: 8 | AE94: 4
A95: 50509 | B95: ชำระค่างวด อีซี่ อินชัวร์ โบรกเกอร์(กท-ตจว) | C95: 42186 | E95: Closed | F95: OFFLINE | G95: บริการรับชำระ | H95: Loan | M95: 0 | N95: 0 | O95: 0 | P95: 100000 | T95: YES | U95: #N/A | V95: =VLOOKUP(A95,'2023 Stats'!$B$2:$D$192,3,FALSE) -> #N/A | W95: #N/A | Y95: #N/A | Z95: #N/A | AB95: #N/A | AE95: #N/A
A96: 50512 | B96: ชำระค่างวด แสททิสบาย(กท-ตจว) | C96: 42186 | E96: Closed | F96: OFFLINE | G96: บริการรับชำระ | H96: Loan | M96: 0 | N96: 0 | O96: 0 | P96: 100000 | T96: YES | U96: #N/A | V96: =VLOOKUP(A96,'2023 Stats'!$B$2:$D$192,3,FALSE) -> #N/A | W96: #N/A | Y96: #N/A | Z96: #N/A | AB96: #N/A | AE96: #N/A
A97: 50515 | B97: ค่าเบี้ยประกันภัย ACE LIFE ASSURANCE | C97: 42186 | E97: Closed | F97: OFFLINE | G97: บริการรับชำระ | H97: Insurance | M97: 0 | N97: 1 | O97: 50000 | P97: 100000 | T97: YES | U97: #N/A | V97: =VLOOKUP(A97,'2023 Stats'!$B$2:$D$192,3,FALSE) -> #N/A | W97: #N/A | Y97: #N/A | Z97: #N/A | AB97: #N/A | AE97: #N/A
A98: 50517 | B98: ชำระค่างวด บ.บีทีเวิลด์ลีส จำกัด | C98: 42186 | E98: Open | F98: OFFLINE | G98: บริการรับชำระ | H98: Loan | M98: 15,20 | N98: 1 | O98: 50000 | P98: 100000 | T98: YES | U98: 31/12/2023 | V98: =VLOOKUP(A98,'2023 Stats'!$B$2:$D$192,3,FALSE) -> 365 | W98: 91 | Y98: 732 | Z98: 61 | AB98: 1366 | AC98: 114 | AE98: 89
A99: 50518 | B99: ชำระค่างวด บ.บีทีเวิลด์ลีส จำกัด ตจว. | C99: 42011 | E99: Closed | F99: OFFLINE | G99: บริการรับชำระ | H99: Loan | M99: 20 | N99: 0 | O99: 50000 | P99: 100000 | V99: =VLOOKUP(A99,'2023 Stats'!$B$2:$D$192,3,FALSE) -> #N/A
A100: 50521 | B100: เมืองไทยประกันภัย จำกัด (มหาชน) | C100: 42186 | E100: Open | F100: OFFLINE | G100: บริการรับชำระ | H100: Insurance | M100: 0 | N100: 1 | O100: 50000 | P100: 100000 | T100: YES | U100: 31/12/2023 | V100: =VLOOKUP(A100,'2023 Stats'!$B$2:$D$192,3,FALSE) -> 1 | W100: 0 | Y100: 3 | Z100: 0 | AB100: 2 | AC100: 0 | AE100: 0
...

Sheet 2023 Stats
A1: No | B1: ITEM_CODE | C1: ITEM_NAME | D1: COUNT(*)
A2: 1 | B2: 52021 | C2: ลูกหนี้ค่าฝากส่งเงินเชื่อ (WEB AR) | D2: 217269
A3: 2 | B3: 90037 | C3: รับเงินฝากธ.กรุงไทย(คีย์เลขที่บ/ช) | D3: 183318
A4: 3 | B4: 51074 | C4: ค่าไฟฟ้าส่วนภูมิภาค (บาร์โค๊ดใหม่BOT) | D4: 141687
A5: 4 | B5: 52047 | C5: ค่าปรับจราจร | D5: 134421
A6: 5 | B6: 50982 | C6: ค่าน้ำประปาส่วนภูมิภาค 1 Bar สาขาใหม่ | D6: 63548
A7: 6 | B7: 50787 | C7: วีซ่า/มาสเตอร์ (Visa/Master) มีบาร์โค้ด | D7: 50402
A8: 7 | B8: 50489 | C8: ชำระค่างวดรถ โตโยต้า ลีสซิ่ง(กท-ตจว) | D8: 45466
A9: 8 | B9: 90028 | C9: รับเงินฝากธ.กสิกรไทย(คีย์เลขที่บ/ช) | D9: 44146
A10: 9 | B10: 52043 | C10: ชำระสินเชื่อรถยนต์ (กท-ตจว) | D10: 39575
A11: 10 | B11: 90022 | C11: AIS 3G Online ไม่มีบาร์ | D11: 35899
A12: 11 | B12: 50961 | C12: ชำระเงินธนาคารอาคารสงเคราะห์(ออนไลน์) | D12: 34946
A13: 12 | B13: 50496 | C13: เงินสมทบประกันสังคมของผู้ประกันตน ม.39 | D13: 32704
... A192: 191 | B192: 50259 | C192: ชำระค่าเบี้ยประกันกรุงเทพประกันชีวิต | D192: 1

Sheet 2025 Stats
A1: บริการหลัก | B1: ปี 2568/2025 | C1: Item ID | D1: จำนวนรายการ (ม.ค.-ต.ค.) | E1: มกราคม | H1: กุมภาพันธ์ | K1: มีนาคม | N1: เมษายน | Q1: พฤษภาคม | T1: มิถุนายน | W1: กรกฎาคม | Z1: สิงหาคม | AC1: กันยายน | AF1: ตุลาคม
B2: Service Name | E2: จำนวนเงิน | F2: ปริมาณงาน | G2: รายได้ | H2: จำนวนเงิน | I2: ปริมาณงาน | J2: รายได้ | K2: จำนวนเงิน | L2: ปริมาณงาน | M2: รายได้ | N2: จำนวนเงิน | O2: ปริมาณงาน | P2: รายได้ | Q2: จำนวนเงิน | R2: ปริมาณงาน | S2: รายได้ | T2: จำนวนเงิน | U2: ปริมาณงาน | V2: รายได้ | W2: จำนวนเงิน | X2: ปริมาณงาน | Y2: รายได้ | Z2: จำนวนเงิน | AA2: ปริมาณงาน | AB2: รายได้ | AC2: จำนวนเงิน | AD2: ปริมาณงาน | AE2: รายได้ | AF2: จำนวนเงิน | AG2: ปริมาณงาน | AH2: รายได้
A3: Western Union | B3: จ่ายเงินธนาณัติระหว่างประเทศ WESTERN UNION | C3: 19032 | D3: =SUM(F3,I3,L3,O3,R3,U3,X3,AA3,AD3,AG3) -> 145223 | E3: 126449573 | F3: 12238 | G3: 1898015 | H3: 112080165 | I3: 11219 | J3: 1702391 | K3: 132021837 | L3: 12818 | M3: 2029661 | N3: 361151965 | O3: 35685 | P3: 5684451 | Q3: 124356689 | R3: 12546 | S3: 1972569 | T3: 119613225 | U3: 12446 | V3: 1915200 | W3: 119804395 | X3: 12621 | Y3: 1899667 | Z3: 112382934 | AA3: 11777 | AB3: 1759991 | AC3: 111106306 | AD3: 11775 | AE3: 1744918 | AF3: 119041492 | AG3: 12098 | AH3: 1894896
B4: รับฝากธนาณัติระหว่างประเทศ WESTERN UNION | C4: 19035 | D4: =SUM(F4,I4,L4,O4,R4,U4,X4,AA4,AD4,AG4) -> 7265 | E4: 7467184 | F4: 657 | G4: 181529 | H4: 6796213 | I4: 646 | J4: 184943 | K4: 6567105 | L4: 624 | M4: 168858 | N4: 19061731 | O4: 1656 | P4: 447361 | Q4: 6864099 | R4: 618 | S4: 155490 | T4: 7207824 | U4: 558 | V4: 177817 | W4: 6798121 | X4: 598 | Y4: 172159 | Z4: 7378287 | AA4: 643 | AB4: 182331 | AC4: 8037178 | AD4: 652 | AE4: 200931 | AF4: 7242183 | AG4: 613 | AH4: 170432
A5: Pay@Post | B5: รับชำระค่าสินค้าเรียกเก็บเงินที่บ้าน(TND) | C5: 362752 | D5: =SUM(F5,I5,L5,O5,R5,U5,X5,AA5,AD5,AG5) -> 2064577 | E5: 428167553 | F5: 196216 | G5: 0 | H5: 368062072 | I5: 177708 | J5: 0 | K5: 379128108 | L5: 194366 | M5: 0 | N5: 717444287 | O5: 348662 | P5: 0 | Q5: 391213944 | R5: 195767 | S5: 0 | T5: 347957806 | U5: 181632 | V5: 0 | W5: 366374982 | X5: 188753 | Y5: 0 | Z5: 369630864 | AA5: 189318 | AB5: 0 | AC5: 376295880 | AD5: 191963 | AE5: 0 | AF5: 398006024 | AG5: 200192 | AH5: 0
B6: รับเงินฝากธ.กรุงไทย(คีย์เลขที่บ/ช) | C6: 356627 | D6: =SUM(F6,I6,L6,O6,R6,U6,X6,AA6,AD6,AG6) -> 176194 | E6: 290141452 | F6: 18950 | G6: 189500 | H6: 273725261 | I6: 17173 | J6: 171730 | K6: 267567240 | L6: 16974 | M6: 169740 | N6: 475683578 | O6: 29902 | P6: 299020 | Q6: 229340943 | R6: 14871 | S6: 148710 | T6: 243120902 | U6: 15714 | V6: 157140 | W6: 226263025 | X6: 15253 | Y6: 152530 | Z6: 218855139 | AA6: 14836 | AB6: 148360 | AC6: 246488755 | AD6: 16468 | AE6: 164680 | AF6: 243473070 | AG6: 16053 | AH6: 160530
B7: การยืนยันตัวตน - แอปฯทางรัฐ (สพร./DGA) | C7: 362522 | D7: =SUM(F7,I7,L7,O7,R7,U7,X7,AA7,AD7,AG7) -> 122563 | E7: 0 | F7: 60166 | G7: 0 | H7: 0 | I7: 36169 | J7: 0 | K7: 0 | L7: 13564 | M7: 0 | N7: 0 | O7: 8532 | P7: 0 | Q7: 0 | R7: 880 | S7: 0 | T7: 0 | U7: 183 | V7: 0 | W7: 0 | X7: 2201 | Y7: 0 | Z7: 0 | AA7: 649 | AB7: 0 | AC7: 0 | AD7: 103 | AE7: 0 | AF7: 0 | AG7: 116 | AH7: 0
B8: ค่าปรับจราจร | C8: 363725 | D8: =SUM(F8,I8,L8,O8,R8,U8,X8,AA8,AD8,AG8) -> 72570 | E8: 6956400 | F8: 13929 | G8: 208935 | H8: 6312300 | I8: 12631 | J8: 189465 | K8: 4864250 | L8: 9693 | M8: 145395 | N8: 6575400 | O8: 12994 | P8: 194910 | Q8: 3440850 | R8: 6795 | S8: 101925 | T8: 2574000 | U8: 5082 | V8: 76230 | W8: 1683100 | X8: 3293 | Y8: 49395 | Z8: 1325700 | AA8: 2640 | AB8: 39600 | AC8: 1447200 | AD8: 2873 | AE8: 43095 | AF8: 1332900 | AG8: 2640 | AH8: 39600
B9: ชำระค่าปรับจราจรไม่ยึดใบขับขี่ | C9: 3421 | D9: =SUM(F9,I9,L9,O9,R9,U9,X9,AA9,AD9,AG9) -> 57655 | E9: 4159102 | F9: 7588 | G9: 225720 | H9: 3898100 | I9: 6290 | J9: 182248 | K9: 3673611 | L9: 6021 | M9: 175648 | N9: 6766551 | O9: 12074 | P9: 366256 | Q9: 3104089 | R9: 5344 | S9: 153824 | T9: 3804055 | U9: 6182 | V9: 183304 | W9: 2081800 | X9: 3313 | Y9: 76956 | Z9: 1581600 | AA9: 2482 | AB9: 51568 | AC9: 1846700 | AD9: 2937 | AE9: 60852 | AF9: 3575221 | AG9: 5424 | AH9: 160336
B10: ชำระค่าสินค้า/บริการ123Service มีบาร์ | C10: 3164 | D10: =SUM(F10,I10,L10,O10,R10,U10,X10,AA10,AD10,AG10) -> 53667 | E10: 22868364 | F10: 6402 | G10: 0 | H10: 16664688 | I10: 5021 | J10: 0 | K10: 16228458 | L10: 5042 | M10: 0 | N10: 31427271 | O10: 8832 | P10: 0 | Q10: 14012146 | R10: 4475 | S10: 0 | T10: 15786988 | U10: 4763 | V10: 0 | W10: 15238943 | X10: 4499 | Y10: 0 | Z10: 15150968 | AA10: 4568 | AB10: 0 | AC10: 17380717 | AD10: 5152 | AE10: 0 | AF10: 15770989 | AG10: 4913 | AH10: 0
B11: รับเงินฝากธ.กสิกรไทย(คีย์เลขที่บ/ช) | C11: 356625 | D11: =SUM(F11,I11,L11,O11,R11,U11,X11,AA11,AD11,AG11) -> 39355 | E11: 52755328 | F11: 3886 | G11: 38860 | H11: 47598755 | I11: 3583 | J11: 35830 | K11: 49353925 | L11: 3663 | M11: 36630 | N11: 92693039 | O11: 6784 | P11: 67840 | Q11: 44732688 | R11: 3380 | S11: 33800 | T11: 46554937 | U11: 3527 | V11: 35270 | W11: 47773992 | X11: 3523 | Y11: 35230 | Z11: 43755867 | AA11: 3454 | AB11: 34540 | AC11: 46075193 | AD11: 3771 | AE11: 37710 | AF11: 50110641 | AG11: 3784 | AH11: 37840
B12: ค่าไฟฟ้าส่วนภูมิภาค (Online) | C12: 364371 | D12: =SUM(F12,I12,L12,O12,R12,U12,X12,AA12,AD12,AG12) -> 36538 | E12: 2001444 | F12: 3011 | G12: 30110 | H12: 1847726 | I12: 3042 | J12: 30420 | K12: 2543894 | L12: 3073 | M12: 30730 | N12: 5714910 | O12: 6658 | P12: 66580 | Q12: 3102744 | R12: 3366 | S12: 33660 | T12: 2826100 | U12: 3408 | V12: 34080 | W12: 2763685 | X12: 3420 | Y12: 34200 | Z12: 2844540 | AA12: 3387 | AB12: 33870 | AC12: 2724182 | AD12: 3604 | AE12: 36040 | AF12: 2748268 | AG12: 3569 | AH12: 35690
B13: ค่าน้ำประปาส่วนภูมิภาค 1 Bar สาขาใหม่ | C13: 3181 | D13: =SUM(F13,I13,L13,O13,R13,U13,X13,AA13,AD13,AG13) -> 34717 | E13: 1267077 | F13: 3370 | G13: 33670 | H13: 1192345 | I13: 3487 | J13: 34840 | K13: 1053351 | L13: 3398 | M13: 33940 | N13: 2313389 | O13: 6306 | P13: 63020 | Q13: 1034513 | R13: 3049 | S13: 30450 | T13: 1025221 | U13: 3136 | V13: 31330 | W13: 953938 | X13: 2986 | Y13: 29830 | Z13: 1001292 | AA13: 3024 | AB13: 30210 | AC13: 992529 | AD13: 3050 | AE13: 30460 | AF13: 844982 | AG13: 2911 | AH13: 29070
B14: AIS 3G Online ไม่มีบาร์ | C14: 3261 | D14: =SUM(F14,I14,L14,O14,R14,U14,X14,AA14,AD14,AG14) -> 29771 | E14: 1602880 | F14: 2937 | G14: 44055 | H14: 1441821 | I14: 2609 | J14: 39135 | K14: 1468296 | L14: 2725 | M14: 40875 | N14: 2902221 | O14: 5178 | P14: 77670 | Q14: 1459644 | R14: 2624 | S14: 39360 | T14: 1386497 | U14: 2522 | V14: 37830 | W14: 1437423 | X14: 2588 | Y14: 38820 | Z14: 1439296 | AA14: 2536 | AB14: 38040 | AC14: 1478794 | AD14: 2626 | AE14: 39390 | AF14: 1898543 | AG14: 3426 | AH14: 51390
B15: รับฝากเงินธ. ไทยพาณิชย์(คีย์เลขที่บ/ช) | C15: 356626 | D15: =SUM(F15,I15,L15,O15,R15,U15,X15,AA15,AD15,AG15) -> 29344 | E15: 41750975 | F15: 2918 | G15: 29180 | H15: 40819880 | I15: 2783 | J15: 27830 | K15: 34605878 | L15: 2493 | M15: 24930 | N15: 61166379 | O15: 4300 | P15: 43000 | Q15: 41193612 | R15: 2675 | S15: 26750 | T15: 44441536 | U15: 2885 | V15: 28850 | W15: 44443549 | X15: 2929 | Y15: 29290 | Z15: 45365787 | AA15: 2913 | AB15: 29130 | AC15: 42235987 | AD15: 2933 | AE15: 29330 | AF15: 33171674 | AG15: 2515 | AH15: 25150
B16: รับชำระ Fuze Post | C16: 363745 | D16: =SUM(F16,I16,L16,O16,R16,U16,X16,AA16,AD16,AG16) -> 26847 | E16: 1533986 | F16: 1626 | G16: 0 | H16: 1460626 | I16: 1621 | J16: 0 | K16: 1699522 | L16: 2002 | M16: 0 | N16: 3489860 | O16: 3556 | P16: 0 | Q16: 2066748 | R16: 2338 | S16: 0 | T16: 2331515 | U16: 2926 | V16: 0 | W16: 2347219 | X16: 3073 | Y16: 0 | Z16: 2248448 | AA16: 2923 | AB16: 0 | AC16: 2534749 | AD16: 3456 | AE16: 0 | AF16: 2413125 | AG16: 3326 | AH16: 0
B17: ชำระเงินบัตรเครดิตธนาคารUOBธ.เอเซียเดิม | C17: 3323 | D17: =SUM(F17,I17,L17,O17,R17,U17,X17,AA17,AD17,AG17) -> 25595 | E17: 23213116 | F17: 2735 | G17: 27350 | H17: 23067115 | I17: 2746 | J17: 27460 | K17: 23876179 | L17: 2890 | M17: 28900 | N17: 43624190 | O17: 5588 | P17: 55880 | Q17: 21852242 | R17: 2774 | S17: 27740 | T17: 22242576 | U17: 2704 | V17: 27040 | W17: 23972051 | X17: 2803 | Y17: 28030 | Z17: 19684299 | AA17: 2376 | AB17: 23760 | AC17: 8199053 | AD17: 979 | AE17: 9790
B18: ชำระค่างวดรถ โตโยต้า ลีสซิ่ง(กท-ตจว) | C18: 2891 | D18: =SUM(F18,I18,L18,O18,R18,U18,X18,AA18,AD18,AG18) -> 23441 | E18: 39513006 | F18: 2741 | G18: 40295 | H18: 35007864 | I18: 2509 | J18: 36845 | K18: 33487188 | L18: 2387 | M18: 35025 | N18: 53877249 | O18: 4310 | P18: 63310 | Q18: 23911224 | R18: 2034 | S18: 29880 | T18: 21760177 | U18: 1967 | V18: 28810 | W18: 22201887 | X18: 1941 | Y18: 28500 | Z18: 20626224 | AA18: 1808 | AB18: 26500 | AC18: 20845610 | AD18: 1869 | AE18: 27465 | AF18: 22215041 | AG18: 1875 | AH18: 27550
B19: เงินสมทบประกันสังคมของผู้ประกันตน ม.39 | C19: 2895 | D19: =SUM(F19,I19,L19,O19,R19,U19,X19,AA19,AD19,AG19) -> 22444 | E19: 772237 | F19: 2490 | G19: 24900 | H19: 768493 | I19: 2494 | J19: 24940 | K19: 715671 | L19: 2312 | M19: 23120 | N19: 1618610 | O19: 4110 | P19: 41100 | Q19: 835920 | R19: 1935 | S19: 19350 | T19: 799632 | U19: 1851 | V19: 18510 | W19: 807408 | X19: 1869 | Y19: 18690 | Z19: 792720 | AA19: 1835 | AB19: 18350 | AC19: 763776 | AD19: 1768 | AE19: 17680 | AF19: 768960 | AG19: 1780 | AH19: 17800
B20: ชำระสินเชื่อรถยนต์ (กท-ตจว) | C20: 360014 | D20: =SUM(F20,I20,L20,O20,R20,U20,X20,AA20,AD20,AG20) -> 19879 | E20: 21767254 | F20: 2133 | G20: 31515 | H20: 19555525 | I20: 1998 | J20: 29470 | K20: 19430466 | L20: 1986 | M20: 29215 | N20: 35114424 | O20: 3690 | P20: 54340 | Q20: 16693607 | R20: 1772 | S20: 26095 | T20: 15764537 | U20: 1716 | V20: 25280 | W20: 15331926 | X20: 1717 | Y20: 25235 | Z20: 14563695 | AA20: 1614 | AB20: 23785 | AC20: 15852473 | AD20: 1664 | AE20: 24470 | AF20: 14728848 | AG20: 1589 | AH20: 23380
B21: สินเชื่อรถยนต์ ธนาคารกรุงศรีอยุธยา | C21: 3191 | D21: =SUM(F21,I21,L21,O21,R21,U21,X21,AA21,AD21,AG21) -> 19145 | E21: 16644373 | F21: 2169 | G21: 21690 | H21: 15423398 | I21: 1954 | J21: 19540 | K21: 15302490 | L21: 1996 | M21: 19960 | N21: 27275365 | O21: 3596 | P21: 35960 | Q21: 12480566 | R21: 1647 | S21: 16470 | T21: 12864847 | U21: 1669 | V21: 16690 | W21: 12247057 | X21: 1609 | Y21: 16090 | Z21: 10986426 | AA21: 1497 | AB21: 14970 | AC21: 11224512 | AD21: 1502 | AE21: 15020 | AF21: 11075927 | AG21: 1506 | AH21: 15060
B22: ชำระบริการต่าง ๆ ของคุรุสภา มีบาร์โค้ด | C22: 30119 | D22: =SUM(F22,I22,L22,O22,R22,U22,X22,AA22,AD22,AG22) -> 18813 | E22: 907700 | F22: 2359 | G22: 23590 | H22: 784900 | I22: 2074 | J22: 20740 | K22: 963600 | L22: 2336 | M22: 23360 | N22: 2417600 | O22: 4510 | P22: 45100 | Q22: 1277800 | R22: 1964 | S22: 19640 | T22: 845100 | U22: 1403 | V22: 14030 | W22: 719200 | X22: 1256 | Y22: 12560 | Z22: 685500 | AA22: 1218 | AB22: 12180 | AC22: 530100 | AD22: 844 | AE22: 8440 | AF22: 504700 | AG22: 849 | AH22: 8490
B23: ชำระเงินธนาคารอาคารสงเคราะห์(ออนไลน์) | C23: 3169 | D23: =SUM(F23,I23,L23,O23,R23,U23,X23,AA23,AD23,AG23) -> 18649 | E23: 8458532 | F23: 1915 | G23: 19150 | H23: 8257414 | I23: 1814 | J23: 18140 | K23: 8672526 | L23: 1826 | M23: 18260 | N23: 15427079 | O23: 3498 | P23: 34980 | Q23: 7658460 | R23: 1669 | S23: 16690 | T23: 7083825 | U23: 1600 | V23: 16000 | W23: 7021054 | X23: 1663 | Y23: 16630 | Z23: 6814313 | AA23: 1584 | AB23: 15840 | AC23: 6527255 | AD23: 1545 | AE23: 15450 | AF23: 6822562 | AG23: 1535 | AH23: 15350
B24: ชำระค่างวด บ.ตรีเพชรอีซูซุลิสซิ่ง จำกัด | C24: 3210 | D24: =SUM(F24,I24,L24,O24,R24,U24,X24,AA24,AD24,AG24) -> 17098 | E24: 21261876 | F24: 1794 | G24: 26910 | H24: 21035348 | I24: 1704 | J24: 25560 | K24: 18596224 | L24: 1594 | M24: 23910 | N24: 35946136 | O24: 3160 | P24: 47400 | Q24: 15229854 | R24: 1450 | S24: 21750 | T24: 14991108 | U24: 1408 | V24: 21120 | W24: 15395950 | X24: 1472 | Y24: 22080 | Z24: 13951522 | AA24: 1364 | AB24: 20460 | AC24: 14630818 | AD24: 1480 | AE24: 22200 | AF24: 17464378 | AG24: 1672 | AH24: 25080
B25: ค่าโทรศัพท์ TOT ใหม่ | C25: 2829 | D25: =SUM(F25,I25,L25,O25,R25,U25,X25,AA25,AD25,AG25) -> 16911 | E25: 699312 | F25: 1762 | G25: 17620 | H25: 612544 | I25: 1611 | J25: 16110 | K25: 648339 | L25: 1663 | M25: 16630 | N25: 1185623 | O25: 3010 | P25: 30100 | Q25: 564058 | R25: 1471 | S25: 14710 | T25: 570077 | U25: 1458 | V25: 14580 | W25: 575383 | X25: 1466 | Y25: 14660 | Z25: 580327 | AA25: 1524 | AB25: 15240 | AC25: 573857 | AD25: 1467 | AE25: 14670 | AF25: 576034 | AG25: 1479 | AH25: 14790
B26: ชำระค่าบริการ บัตรชำระบุญเติม มีบาร์ | C26: 2684 | D26: =SUM(F26,I26,L26,O26,R26,U26,X26,AA26,AD26,AG26) -> 15999 | E26: 10270047 | F26: 1667 | G26: 25005 | H26: 8705573 | I26: 1429 | J26: 21435 | K26: 9241770 | L26: 1486 | M26: 22290 | N26: 16698374 | O26: 2590 | P26: 38850 | Q26: 8150452 | R26: 1324 | S26: 19860 | T26: 7971638 | U26: 1252 | V26: 18780 | W26: 7672876 | X26: 1251 | Y26: 18765 | Z26: 7691516 | AA26: 1251 | AB26: 18765 | AC26: 7959499 | AD26: 1350 | AE26: 20250 | AF26: 13285345 | AG26: 2399 | AH26: 35985
B27: ชำระภาษีเงินได้ ภงด. | C27: 2693 | D27: =SUM(F27,I27,L27,O27,R27,U27,X27,AA27,AD27,AG27) -> 15399 | E27: 2844106 | F27: 1520 | G27: 15200 | H27: 4435434 | I27: 1728 | J27: 17280 | K27: 9720563 | L27: 3331 | M27: 33310 | N27: 9848838 | O27: 2902 | P27: 29020 | Q27: 3684101 | R27: 831 | S27: 8310 | T27: 2903262 | U27: 714 | V27: 7140 | W27: 2124468 | X27: 920 | Y27: 9200 | Z27: 2371000 | AA27: 973 | AB27: 9730 | AC27: 2941987 | AD27: 1668 | AE27: 16680 | AF27: 2302499 | AG27: 812 | AH27: 8120
B28: ค่างวดเครื่องจักร/บริการอื่นสยามคูโบต้า | C28: 3129 | D28: =SUM(F28,I28,L28,O28,R28,U28,X28,AA28,AD28,AG28) -> 15154 | E28: 39526216 | F28: 2104 | G28: 21040 | H28: 32591526 | I28: 1796 | J28: 17960 | K28: 29708286 | L28: 1717 | M28: 17170 | N28: 52585953 | O28: 3006 | P28: 30060 | Q28: 24637487 | R28: 1444 | S28: 14440 | T28: 18455550 | U28: 1202 | V28: 12020 | W28: 10990303 | X28: 1055 | Y28: 10550 | Z28: 9017678 | AA28: 931 | AB28: 9310 | AC28: 9192523 | AD28: 950 | AE28: 9500 | AF28: 10708817 | AG28: 949 | AH28: 9490
B29: รับเงินฝากธ.กรุงเทพ(คีย์เลขที่บ/ช) | C29: 356628 | D29: =SUM(F29,I29,L29,O29,R29,U29,X29,AA29,AD29,AG29) -> 10603 | E29: 15368120 | F29: 1125 | G29: 11250 | H29: 12787420 | I29: 965 | J29: 9650 | K29: 12669888 | L29: 971 | M29: 9710 | N29: 26448438 | O29: 1962 | P29: 19620 | Q29: 11017213 | R29: 875 | S29: 8750 | T29: 11671133 | U29: 957 | V29: 9570 | W29: 13191111 | X29: 1023 | Y29: 10230 | Z29: 11108292 | AA29: 824 | AB29: 8240 | AC29: 11602319 | AD29: 907 | AE29: 9070 | AF29: 13369330 | AG29: 994 | AH29: 9940
... B42: รับเงินฝากธ.ซีไอเอ็มบีไทย(คีย์เลขที่บ/ช) | C42: 3254 | D42: =SUM(F42,I42,L42,O42,R42,U42,X42,AA42,AD42,AG42) -> 3911 | E42: 4462571 | F42: 383 | G42: 5745 | H42: 4708398 | I42: 418 | J42: 6270 | K42: 4715743 | L42: 397 | M42: 5955 | N42: 8586739 | O42: 692 | P42: 10380 | Q42: 3232804 | R42: 299 | S42: 4485 | T42: 4488559 | U42: 358 | V42: 5370 | W42: 3771508 | X42: 322 | Y42: 4830 | Z42: 3782661 | AA42: 326 | AB42: 4890 | AC42: 3816133 | AD42: 355 | AE42: 5325 | AF42: 4036360 | AG42: 361 | AH42: 5415
B43: ชำระค่าธรรมเนียม กรมธุรกิจพลังงาน | C43: 364544 | D43: =SUM(F43,I43,L43,O43,R43,U43,X43,AA43,AD43,AG43) -> 3899 | H43: 1484902 | I43: 1156 | J43: 17340 | K43: 778554 | L43: 577 | M43: 8655 | N43: 1509737 | O43: 1018 | P43: 15270 | Q43: 611113 | R43: 444 | S43: 6660 | T43: 329199 | U43: 259 | V43: 3885 | W43: 205503 | X43: 161 | Y43: 2415 | Z43: 190274 | AA43: 123 | AB43: 1845 | AC43: 160320 | AD43: 112 | AE43: 1680 | AF43: 84609 | AG43: 49 | AH43: 735
B44: รับชำระ บัตรเครดิต/บัตรกดเงินสด (กท-ตจว) | C44: 359333 | D44: =SUM(F44,I44,L44,O44,R44,U44,X44,AA44,AD44,AG44) -> 3300 | E44: 1397058 | F44: 377 | G44: 5190 | H44: 1051535 | I44: 290 | J44: 4045 | K44: 1247715 | L44: 317 | M44: 4340 | N44: 2552307 | O44: 642 | P44: 8800 | Q44: 1078835 | R44: 281 | S44: 3925 | T44: 1096253 | U44: 277 | V44: 3810 | W44: 1159283 | X44: 303 | Y44: 4190 | Z44: 987580 | AA44: 266 | AB44: 3695 | AC44: 916453 | AD44: 269 | AE44: 3760 | AF44: 1327679 | AG44: 278 | AH44: 3830
B45: รับเงินฝากธ.กรุงศรีอยุธยา(คีย์เลขที่บ/ช) | C45: 3253 | D45: =SUM(F45,I45,L45,O45,R45,U45,X45,AA45,AD45,AG45) -> 3261 | E45: 5800672 | F45: 307 | G45: 3070 | H45: 5584495 | I45: 293 | J45: 2930 | K45: 5716351 | L45: 289 | M45: 2890 | N45: 13209436 | O45: 606 | P45: 6060 | Q45: 5763751 | R45: 271 | S45: 2710 | T45: 6569577 | U45: 324 | V45: 3240 | W45: 5406548 | X45: 282 | Y45: 2820 | Z45: 5770776 | AA45: 267 | AB45: 2670 | AC45: 6012410 | AD45: 312 | AE45: 3120 | AF45: 5858707 | AG45: 310 | AH45: 3100
B46: ชำระค่างวด AYUDHYA Capital Auto Lease | C46: 2689 | D46: =SUM(F46,I46,L46,O46,R46,U46,X46,AA46,AD46,AG46) -> 3200 | E46: 730765 | F46: 353 | G46: 3530 | H46: 720234 | I46: 291 | J46: 2910 | K46: 838939 | L46: 301 | M46: 3010 | N46: 1390369 | O46: 582 | P46: 5820 | Q46: 625554 | R46: 313 | S46: 3130 | T46: 570117 | U46: 283 | V46: 2830 | W46: 578144 | X46: 270 | Y46: 2700 | Z46: 518160 | AA46: 259 | AB46: 2590 | AC46: 545172 | AD46: 282 | AE46: 2820 | AF46: 594793 | AG46: 266 | AH46: 2660
B47: ชำระค่าบริการ บัตรชำระบุญเติม ไม่มีบาร์ | C47: 2692 | D47: =SUM(F47,I47,L47,O47,R47,U47,X47,AA47,AD47,AG47) -> 2789 | E47: 1641323 | F47: 303 | G47: 4545 | H47: 1483220 | I47: 254 | J47: 3810 | K47: 1421689 | L47: 269 | M47: 4035 | N47: 2893460 | O47: 460 | P47: 6900 | Q47: 1581250 | R47: 236 | S47: 3540 | T47: 1350983 | U47: 226 | V47: 3390 | W47: 1274520 | X47: 224 | Y47: 3360 | Z47: 1316751 | AA47: 244 | AB47: 3660 | AC47: 1497405 | AD47: 261 | AE47: 3915 | AF47: 1663920 | AG47: 312 | AH47: 4680
B48: ชำระค่าธรรมเนียมโอนชุดวิชา มสธ. | C48: 2928 | D48: =SUM(F48,I48,L48,O48,R48,U48,X48,AA48,AD48,AG48) -> 2604 | E48: 108451 | F48: 234 | G48: 2340 | H48: 89301 | I48: 200 | J48: 2000 | K48: 119500 | L48: 302 | M48: 3020 | N48: 143600 | O48: 234 | P48: 2340 | Q48: 63250 | R48: 116 | S48: 1160 | T48: 270000 | U48: 619 | V48: 6190 | W48: 119800 | X48: 251 | Y48: 2510 | Z48: 118400 | AA48: 284 | AB48: 2840 | AC48: 122900 | AD48: 278 | AE48: 2780 | AF48: 39500 | AG48: 86 | AH48: 860
B49: ชำระค่าเช่าที่ราชพัสดุ กรมธนารักษ์ | C49: 3036 | D49: =SUM(F49,I49,L49,O49,R49,U49,X49,AA49,AD49,AG49) -> 2517 | E49: 484058 | F49: 510 | G49: 7650 | H49: 1456006 | I49: 1099 | J49: 16485 | K49: 288456 | L49: 300 | M49: 4500 | N49: 304926 | O49: 208 | P49: 3120 | Q49: 139601 | R49: 115 | S49: 1725 | T49: 66866 | U49: 72 | V49: 1080 | W49: 183683 | X49: 79 | Y49: 1185 | Z49: 115440 | AA49: 50 | AB49: 750 | AC49: 61153 | AD49: 35 | AE49: 525 | AF49: 120534 | AG49: 49 | AH49: 735
B50: ธนาณัติชำระค่าปรับจราจร | C50: 3406 | D50: =SUM(F50,I50,L50,O50,R50,U50,X50,AA50,AD50,AG50) -> 2476 | E50: 293560 | F50: 417 | G50: 22680 | H50: 374978 | I50: 332 | J50: 18816 | K50: 363190 | L50: 329 | M50: 18480 | N50: 349060 | O50: 536 | P50: 31920 | Q50: 216530 | R50: 248 | S50: 13944 | T50: 121450 | U50: 198 | V50: 10920 | W50: 94162 | X50: 142 | Y50: 5712 | Z50: 39400 | AA50: 64 | AB50: 2184 | AC50: 48300 | AD50: 95 | AE50: 3864 | AF50: 84900 | AG50: 115 | AH50: 7056
B51: ชำระค่าสินค้า ยันมาร์แคปปิตอล | C51: 3067 | D51: =SUM(F51,I51,L51,O51,R51,U51,X51,AA51,AD51,AG51) -> 2433 | E51: 3783098 | F51: 255 | G51: 3825 | H51: 2708709 | I51: 239 | J51: 3585 | K51: 3772849 | L51: 243 | M51: 3645 | N51: 6408420 | O51: 470 | P51: 7050 | Q51: 3755350 | R51: 242 | S51: 3630 | T51: 3260625 | U51: 221 | V51: 3315 | W51: 1665783 | X51: 189 | Y51: 2835 | Z51: 1747946 | AA51: 191 | AB51: 2865 | AC51: 1853744 | AD51: 203 | AE51: 3045 | AF51: 1166932 | AG51: 180 | AH51: 2700
B52: บัครเครดิต KTC Barcode 1 แถว(กท-ตจว) | C52: 2943 | D52: =SUM(F52,I52,L52,O52,R52,U52,X52,AA52,AD52,AG52) -> 2307 | E52: 1295363 | F52: 248 | G52: 4630 | H52: 1160682 | I52: 205 | J52: 3870 | K52: 1242482 | L52: 230 | M52: 4270 | N52: 2077885 | O52: 434 | P52: 8050 | Q52: 1144110 | R52: 210 | S52: 3955 | T52: 865306 | U52: 184 | V52: 3430 | W52: 833130 | X52: 185 | Y52: 3495 | Z52: 934839 | AA52: 185 | AB52: 3475 | AC52: 960373 | AD52: 173 | AE52: 3245 | AF52: 1370471 | AG52: 253 | AH52: 4830
B53: ถอนเงิน EDC ธ.กรุงไทย/Cross bank (ออฟไลน์) | C53: 358864 | D53: =SUM(F53,I53,L53,O53,R53,U53,X53,AA53,AD53,AG53) -> 2142 | E53: -1626845 | F53: 209 | G53: 0 | H53: -1758405 | I53: 220 | J53: 0 | K53: -1544300 | L53: 202 | M53: 0 | N53: -2886102 | O53: 346 | P53: 0 | Q53: -1781939 | R53: 227 | S53: 0 | T53: -1330732 | U53: 168 | V53: 0 | W53: -1487009 | X53: 193 | Y53: 0 | Z53: -1190405 | AA53: 159 | AB53: 0 | AC53: -1698434 | AD53: 195 | AE53: 0 | AF53: -1812373 | AG53: 223 | AH53: 0
B54: สมัครใหม่/ค่าธรรมเนียม/สัมฤทธิ์ ป.ตรีมสธ | C54: 2714 | D54: =SUM(F54,I54,L54,O54,R54,U54,X54,AA54,AD54,AG54) -> 2105 | E54: 476401 | F54: 174 | G54: 1740 | H54: 694350 | I54: 244 | J54: 2440 | K54: 813900 | L54: 401 | M54: 4010 | N54: 639202 | O54: 202 | P54: 2020 | Q54: 438700 | R54: 142 | S54: 1420 | T54: 720200 | U54: 302 | V54: 3020 | W54: 416800 | X54: 150 | Y54: 1500 | Z54: 661600 | AA54: 215 | AB54: 2150 | AC54: 491650 | AD54: 224 | AE54: 2240 | AF54: 91600 | AG54: 51 | AH54: 510
B55: ค่าน้ำประปานครหลวง | C55: 2655 | D55: =SUM(F55,I55,L55,O55,R55,U55,X55,AA55,AD55,AG55) -> 2104 | E55: 89266 | F55: 194 | G55: 1940 | H55: 104228 | I55: 206 | J55: 2060 | K55: 123884 | L55: 203 | M55: 2030 | N55: 291907 | O55: 392 | P55: 3920 | Q55: 108612 | R55: 187 | S55: 1870 | T55: 104576 | U55: 186 | V55: 1860 | W55: 113755 | X55: 190 | Y55: 1900 | Z55: 115331 | AA55: 174 | AB55: 1740 | AC55: 123836 | AD55: 189 | AE55: 1890 | AF55: 102044 | AG55: 183 | AH55: 1830
B56: ชำระค่าสมัคร รร.ไปรษณีย์ (ภาคสมทบ) | C56: 365495 | D56: =SUM(F56,I56,L56,O56,R56,U56,X56,AA56,AD56,AG56) -> 2013 | Z56: 0 | AA56: 1248 | AB56: 249600 | AC56: 0 | AD56: 765 | AE56: 153000
B57: รับชำระค่าสินค้าและบริการ บ. ทริปเปิลที บรอดแบนด์ | C57: 364526 | D57: =SUM(F57,I57,L57,O57,R57,U57,X57,AA57,AD57,AG57) -> 1964 | E57: 164903 | F57: 179 | G57: 2685 | H57: 135373 | I57: 161 | J57: 2415 | K57: 153411 | L57: 174 | M57: 2610 | N57: 323356 | O57: 372 | P57: 5580 | Q57: 146216 | R57: 170 | S57: 2550 | T57: 135839 | U57: 168 | V57: 2520 | W57: 174257 | X57: 201 | Y57: 3015 | Z57: 120364 | AA57: 165 | AB57: 2475 | AC57: 162218 | AD57: 180 | AE57: 2700 | AF57: 151816 | AG57: 194 | AH57: 2910
B58: ชำระค่าขอวีซ่าสถานฑูตญี่ปุ่น(VFS) | C58: 3325 | D58: =SUM(F58,I58,L58,O58,R58,U58,X58,AA58,AD58,AG58) -> 1950 | E58: 324420 | F58: 174 | G58: 11310 | H58: 412395 | I58: 219 | J58: 14235 | K58: 576420 | L58: 324 | M58: 21060 | N58: 503640 | O58: 300 | P58: 19500 | Q58: 198960 | R58: 108 | S58: 7020 | T58: 264535 | U58: 143 | V58: 9295 | W58: 187155 | X58: 103 | Y58: 6695 | Z58: 276435 | AA58: 155 | AB58: 10075 | AC58: 390895 | AD58: 223 | AE58: 14495 | AF58: 356835 | AG58: 201 | AH58: 13065
B59: Ge ค่า First Choice | C59: 2685 | D59: =SUM(F59,I59,L59,O59,R59,U59,X59,AA59,AD59,AG59) -> 1715 | E59: 531516 | F59: 168 | G59: 1680 | H59: 479542 | I59: 161 | J59: 1610 | K59: 496962 | L59: 173 | M59: 1730 | N59: 719358 | O59: 310 | P59: 3100 | Q59: 560488 | R59: 155 | S59: 1550 | T59: 490588 | U59: 154 | V59: 1540 | W59: 491580 | X59: 165 | Y59: 1650 | Z59: 516938 | AA59: 130 | AB59: 1300 | AC59: 294839 | AD59: 146 | AE59: 1460 | AF59: 522290 | AG59: 153 | AH59: 1530
B60: ชำระค่าสมัครเข้าศึกษา รร.ไปรษณีย์ | C60: 30107 | D60: =SUM(F60,I60,L60,O60,R60,U60,X60,AA60,AD60,AG60) -> 1606 | Q60: 0 | R60: 18 | S60: 7200 | T60: 0 | U60: 1588 | V60: 635200
B61: ชำระค่าบัตรเครดิตกรุงศรีอยุธยา | C61: 2851 | D61: =SUM(F61,I61,L61,O61,R61,U61,X61,AA61,AD61,AG61) -> 1603 | E61: 1043124 | F61: 156 | G61: 1560 | H61: 960454 | I61: 146 | J61: 1460 | K61: 818173 | L61: 164 | M61: 1640 | N61: 1704245 | O61: 304 | P61: 3040 | Q61: 783452 | R61: 137 | S61: 1370 | T61: 1474656 | U61: 142 | V61: 1420 | W61: 955230 | X61: 143 | Y61: 1430 | Z61: 777069 | AA61: 126 | AB61: 1260 | AC61: 974938 | AD61: 127 | AE61: 1270 | AF61: 1241324 | AG61: 158 | AH61: 1580
B62: ชำระเงินกู้ธนาคาร SME BANK | C62: 2781 | D62: =SUM(F62,I62,L62,O62,R62,U62,X62,AA62,AD62,AG62) -> 1571 | E62: 3812035 | F62: 169 | G62: 1910 | H62: 4109179 | I62: 155 | J62: 1890 | K62: 5122266 | L62: 150 | M62: 1990 | N62: 6849545 | O62: 288 | P62: 3300 | Q62: 3178762 | R62: 147 | S62: 1640 | T62: 4542725 | U62: 134 | V62: 1800 | W62: 3117790 | X62: 137 | Y62: 1580 | Z62: 2909513 | AA62: 131 | AB62: 1470 | AC62: 3200859 | AD62: 131 | AE62: 1540 | AF62: 2756460 | AG62: 129 | AH62: 1450
B63: เปลี่ยนสาขา,ที่อยู่,ชื่อ_สกุล,ทำบัตรนศ. | C63: 2798 | D63: =SUM(F63,I63,L63,O63,R63,U63,X63,AA63,AD63,AG63) -> 1507 | E63: 16000 | F63: 192 | G63: 1920 | H63: 11700 | I63: 137 | J63: 1370 | K63: 12300 | L63: 159 | M63: 1590 | N63: 16800 | O63: 202 | P63: 2020 | Q63: 13500 | R63: 158 | S63: 1580 | T63: 14300 | U63: 165 | V63: 1650 | W63: 11900 | X63: 155 | Y63: 1550 | Z63: 9800 | AA63: 114 | AB63: 1140 | AC63: 8900 | AD63: 118 | AE63: 1180 | AF63: 9100 | AG63: 107 | AH63: 1070
B64: ตรวจสอบข้อมูลเครดิตบุคคลธรรมดา | C64: 30099 | D64: =SUM(F64,I64,L64,O64,R64,U64,X64,AA64,AD64,AG64) -> 1486 | E64: 27400 | F64: 179 | G64: 0 | H64: 15750 | I64: 105 | J64: 0 | K64: 21250 | L64: 139 | M64: 0 | N64: 37800 | O64: 248 | P64: 0 | Q64: 20500 | R64: 133 | S64: 0 | T64: 23900 | U64: 158 | V64: 0 | W64: 19150 | X64: 127 | Y64: 0 | Z64: 16750 | AA64: 109 | AB64: 0 | AC64: 20300 | AD64: 130 | AE64: 0 | AF64: 24250 | AG64: 158 | AH64: 0
B65: ค่าไฟฟ้านครหลวง (Online) | C65: 365123 | D65: =SUM(F65,I65,L65,O65,R65,U65,X65,AA65,AD65,AG65) -> 1368 | H65: 212 | I65: 1 | J65: 10 | Q65: 779693 | R65: 227 | S65: 2270 | T65: 724244 | U65: 238 | V65: 2380 | W65: 786099 | X65: 232 | Y65: 2320 | Z65: 680860 | AA65: 224 | AB65: 2240 | AC65: 613170 | AD65: 223 | AE65: 2230 | AF65: 642722 | AG65: 223 | AH65: 2230
B66: จองตั๋วรายการบันเทิงและอื่นของ TTM ใหม่ | C66: 3113 | D66: =SUM(F66,I66,L66,O66,R66,U66,X66,AA66,AD66,AG66) -> 1361 | E66: 470160 | F66: 285 | G66: 2850 | H66: 123720 | I66: 28 | J66: 280 | K66: 793500 | L66: 167 | M66: 1670 | N66: 849940 | O66: 80 | P66: 800 | Q66: 714841 | R66: 351 | S66: 3510 | T66: 1129417 | U66: 146 | V66: 1460 | W66: 595160 | X66: 81 | Y66: 810 | Z66: 959560 | AA66: 178 | AB66: 1780 | AC66: 55550 | AD66: 17 | AE66: 170 | AF66: 105180 | AG66: 28 | AH66: 280
B67: ค่าบริการโทรคมฯTBOSSกสท. (ใหม่) | C67: 2834 | D67: =SUM(F67,I67,L67,O67,R67,U67,X67,AA67,AD67,AG67) -> 1324 | E67: 97442 | F67: 128 | G67: 1280 | H67: 72855 | I67: 128 | J67: 1280 | K67: 84935 | L67: 137 | M67: 1370 | N67: 138468 | O67: 218 | P67: 2180 | Q67: 65476 | R67: 115 | S67: 1150 | T67: 84620 | U67: 119 | V67: 1190 | W67: 117129 | X67: 124 | Y67: 1240 | Z67: 69417 | AA67: 120 | AB67: 1200 | AC67: 84170 | AD67: 124 | AE67: 1240 | AF67: 67534 | AG67: 111 | AH67: 1110
B68: ค่าไฟฟ้านครหลวง | C68: 2654 | D68: =SUM(F68,I68,L68,O68,R68,U68,X68,AA68,AD68,AG68) -> 1128 | E68: 562326 | F68: 244 | G68: 2440 | H68: 550892 | I68: 237 | J68: 2370 | K68: 689449 | L68: 251 | M68: 2510 | N68: 1295865 | O68: 396 | P68: 3960
B69: ชำระเบี้ยประกัน บ.ทีคิวเอ็ม โบรคเกอร์ฯ | C69: 3166 | D69: =SUM(F69,I69,L69,O69,R69,U69,X69,AA69,AD69,AG69) -> 1074 | E69: 636415 | F69: 159 | G69: 2385 | H69: 449696 | I69: 123 | J69: 1845 | K69: 397480 | L69: 96 | M69: 1440 | N69: 590576 | O69: 160 | P69: 2400 | Q69: 297133 | R69: 84 | S69: 1260 | T69: 271905 | U69: 71 | V69: 1065 | W69: 313927 | X69: 84 | Y69: 1260 | Z69: 268106 | AA69: 85 | AB69: 1275 | AC69: 291123 | AD69: 92 | AE69: 1380 | AF69: 374540 | AG69: 120 | AH69: 1800
B70: ค่าสมัครสอบเข้าทำงานเป็นพนักงานไปรษณีย์ | C70: 30106 | D70: =SUM(F70,I70,L70,O70,R70,U70,X70,AA70,AD70,AG70) -> 1015 | T70: 0 | U70: 479 | V70: 143700 | W70: 0 | X70: 536 | Y70: 160800
B71: ชำระค่างวด/เบี้ยฯ/ต่อทะเบียนรถ BAR 1 แถว | C71: 3114 | D71: =SUM(F71,I71,L71,O71,R71,U71,X71,AA71,AD71,AG71) -> 1006 | E71: 2500024 | F71: 115 | G71: 1150 | H71: 2148072 | I71: 93 | J71: 930 | K71: 2607889 | L71: 104 | M71: 1040 | N71: 4278332 | O71: 174 | P71: 1740 | Q71: 2037297 | R71: 88 | S71: 880 | T71: 1837165 | U71: 81 | V71: 810 | W71: 1621036 | X71: 72 | Y71: 720 | Z71: 2019110 | AA71: 88 | AB71: 880 | AC71: 2133827 | AD71: 94 | AE71: 940 | AF71: 2270041 | AG71: 97 | AH71: 970
B72: ส่งเงินสะสมเข้ากองทุนการออมแห่งชาติ | C72: 35699 | D72: =SUM(F72,I72,L72,O72,R72,U72,X72,AA72,AD72,AG72) -> 876 | E72: 37400 | F72: 92 | G72: 0 | H72: 26000 | I72: 80 | J72: 0 | K72: 25450 | L72: 82 | M72: 0 | N72: 45400 | O72: 164 | P72: 0 | Q72: 26950 | R72: 79 | S72: 0 | T72: 20200 | U72: 68 | V72: 0 | W72: 63500 | X72: 80 | Y72: 0 | Z72: 25410 | AA72: 72 | AB72: 0 | AC72: 65250 | AD72: 80 | AE72: 0 | AF72: 70250 | AG72: 79 | AH72: 0
B73: ถอนเงิน ธ.กสิกรไทย จำกัด | C73: 357221 | D73: =SUM(F73,I73,L73,O73,R73,U73,X73,AA73,AD73,AG73) -> 864 | E73: -437896 | F73: 110 | G73: 1100 | H73: -321730 | I73: 79 | J73: 790 | K73: -232157 | L73: 61 | M73: 610 | N73: -589220 | O73: 152 | P73: 1520 | Q73: -287300 | R73: 81 | S73: 810 | T73: -315186 | U73: 107 | V73: 1070 | W73: -285626 | X73: 78 | Y73: 780 | Z73: -156488 | AA73: 53 | AB73: 530 | AC73: -282250 | AD73: 80 | AE73: 800 | AF73: -225646 | AG73: 63 | AH73: 630
B74: ใบรายงานผลฯ/หนังสือรับรอง บ10ป.โท-เอก | C74: 2892 | D74: =SUM(F74,I74,L74,O74,R74,U74,X74,AA74,AD74,AG74) -> 847 | E74: 46200 | F74: 87 | G74: 870 | H74: 34700 | I74: 72 | J74: 720 | K74: 74700 | L74: 154 | M74: 1540 | N74: 78000 | O74: 170 | P74: 1700 | Q74: 28300 | R74: 56 | S74: 560 | T74: 20300 | U74: 41 | V74: 410 | W74: 16800 | X74: 35 | Y74: 350 | Z74: 25400 | AA74: 46 | AB74: 460 | AC74: 59200 | AD74: 104 | AE74: 1040 | AF74: 40100 | AG74: 82 | AH74: 820
B75: ชำระค่าบัตรเครดิต TESCO VISA CARD | C75: 2810 | D75: =SUM(F75,I75,L75,O75,R75,U75,X75,AA75,AD75,AG75) -> 828 | E75: 330580 | F75: 80 | G75: 800 | H75: 196455 | I75: 57 | J75: 570 | K75: 305518 | L75: 63 | M75: 630 | N75: 488991 | O75: 138 | P75: 1380 | Q75: 265195 | R75: 70 | S75: 700 | T75: 159270 | U75: 52 | V75: 520 | W75: 207493 | X75: 62 | Y75: 620 | Z75: 185431 | AA75: 51 | AB75: 510 | AC75: 325398 | AD75: 63 | AE75: 630 | AF75: 983417 | AG75: 192 | AH75: 1920
B76: ชำระเบี้ยประกันเมืองไทยประกันชีวิต | C76: 2953 | D76: =SUM(F76,I76,L76,O76,R76,U76,X76,AA76,AD76,AG76) -> 816 | E76: 185878 | F76: 74 | G76: 1110 | H76: 235693 | I76: 82 | J76: 1230 | K76: 208390 | L76: 69 | M76: 1035 | N76: 495664 | O76: 154 | P76: 2310 | Q76: 195335 | R76: 77 | S76: 1155 | T76: 260371 | U76: 85 | V76: 1275 | W76: 298434 | X76: 78 | Y76: 1170 | Z76: 177480 | AA76: 60 | AB76: 900 | AC76: 246104 | AD76: 75 | AE76: 1125 | AF76: 256885 | AG76: 62 | AH76: 930
B77: ค่าผลิตภัณฑ์มิสทีน (Mistine) (กทม-ตจว) | C77: 3045 | D77: =SUM(F77,I77,L77,O77,R77,U77,X77,AA77,AD77,AG77) -> 800 | E77: 86009 | F77: 91 | G77: 1320 | H77: 70472 | I77: 74 | J77: 1085 | K77: 72524 | L77: 77 | M77: 1125 | N77: 158908 | O77: 158 | P77: 2330 | Q77: 58590 | R77: 61 | S77: 895 | T77: 66749 | U77: 71 | V77: 1045 | W77: 78731 | X77: 77 | Y77: 1130 | Z77: 55742 | AA77: 65 | AB77: 950 | AC77: 71763 | AD77: 71 | AE77: 1045 | AF77: 56322 | AG77: 55 | AH77: 800
B78: ชำระค่างวดรถ นิสสัน ลีสซิ่ง(กท-ตจว) | C78: 2967 | D78: =SUM(F78,I78,L78,O78,R78,U78,X78,AA78,AD78,AG78) -> 798 | E78: 864313 | F78: 87 | G78: 1265 | H78: 890933 | I78: 87 | J78: 1265 | K78: 611986 | L78: 66 | M78: 960 | N78: 1339239 | O78: 142 | P78: 2060 | Q78: 551259 | R78: 68 | S78: 995 | T78: 486500 | U78: 66 | V78: 950 | W78: 603741 | X78: 79 | Y78: 1150 | Z78: 606258 | AA78: 71 | AB78: 1030 | AC78: 518792 | AD78: 66 | AE78: 975 | AF78: 507771 | AG78: 66 | AH78: 975
B79: ชำระค่าจัดส่งเอกสารกรมการขนส่ง | C79: 365067 | D79: =SUM(F79,I79,L79,O79,R79,U79,X79,AA79,AD79,AG79) -> 779 | E79: 2336 | F79: 73 | G79: 0 | H79: 2592 | I79: 81 | J79: 0 | K79: 2912 | L79: 91 | M79: 0 | N79: 4544 | O79: 142 | P79: 0 | Q79: 2560 | R79: 80 | S79: 0 | T79: 2816 | U79: 88 | V79: 0 | W79: 2528 | X79: 79 | Y79: 0 | Z79: 1504 | AA79: 47 | AB79: 0 | AC79: 1280 | AD79: 40 | AE79: 0 | AF79: 1856 | AG79: 58 | AH79: 0
B80: ชำระภาษีรถยนต์ กรมการขนส่ง | C80: 364823 | D80: =SUM(F80,I80,L80,O80,R80,U80,X80,AA80,AD80,AG80) -> 779 | E80: 116464 | F80: 73 | G80: 1460 | H80: 145843 | I80: 81 | J80: 1620 | K80: 161878 | L80: 91 | M80: 1820 | N80: 218801 | O80: 142 | P80: 2840 | Q80: 122082 | R80: 80 | S80: 1600 | T80: 133691 | U80: 88 | V80: 1760 | W80: 127136 | X80: 79 | Y80: 1580 | Z80: 66634 | AA80: 47 | AB80: 940 | AC80: 69699 | AD80: 40 | AE80: 800 | AF80: 84746 | AG80: 58 | AH80: 1160
B81: ชำระค่าสินค้าและบริการ ดีแทคไตรเน็ต | C81: 3183 | D81: =SUM(F81,I81,L81,O81,R81,U81,X81,AA81,AD81,AG81) -> 763 | E81: 36827 | F81: 83 | G81: 1245 | H81: 30764 | I81: 73 | J81: 1095 | K81: 36222 | L81: 78 | M81: 1170 | N81: 66716 | O81: 152 | P81: 2280 | Q81: 35644 | R81: 69 | S81: 1035 | T81: 34481 | U81: 71 | V81: 1065 | W81: 31892 | X81: 67 | Y81: 1005 | Z81: 30161 | AA81: 56 | AB81: 840 | AC81: 23381 | AD81: 54 | AE81: 810 | AF81: 29049 | AG81: 60 | AH81: 900
B82: สินเชื่อ/ประกัน/อื่นๆ TISCO BANK | C82: 2995 | D82: =SUM(F82,I82,L82,O82,R82,U82,X82,AA82,AD82,AG82) -> 744 | E82: 5963413 | F82: 744 | G82: 11160
B83: ค่าธรรมเนียมพรบ.ควบคุมน้ำมันเชื้อเพลิง42 | C83: 2790 | D83: =SUM(F83,I83,L83,O83,R83,U83,X83,AA83,AD83,AG83) -> 697 | E83: 228310 | F83: 287 | G83: 8610 | H83: 127370 | I83: 137 | J83: 4110 | K83: 57510 | L83: 66 | M83: 1980 | N83: 39300 | O83: 58 | P83: 1740 | Q83: 31180 | R83: 43 | S83: 1290 | T83: 15700 | U83: 24 | V83: 720 | W83: 11250 | X83: 20 | Y83: 600 | Z83: 11900 | AA83: 20 | AB83: 600 | AC83: 9300 | AD83: 17 | AE83: 510 | AF83: 14200 | AG83: 25 | AH83: 750
B84: เซ็นทรัลมาสเตอร์คาร์ด (MasterCard) | C84: 2850 | D84: =SUM(F84,I84,L84,O84,R84,U84,X84,AA84,AD84,AG84) -> 634 | E84: 392817 | F84: 60 | G84: 600 | H84: 418470 | I84: 61 | J84: 610 | K84: 498727 | L84: 62 | M84: 620 | N84: 923933 | O84: 120 | P84: 1200 | Q84: 332563 | R84: 58 | S84: 580 | T84: 382681 | U84: 49 | V84: 490 | W84: 440030 | X84: 59 | Y84: 590 | Z84: 426981 | AA84: 53 | AB84: 530 | AC84: 342558 | AD84: 53 | AE84: 530 | AF84: 300892 | AG84: 59 | AH84: 590
B85: รับชำระค่าเบี้ยประกันภัย ทิพยประกันภัย | C85: 3141 | D85: =SUM(F85,I85,L85,O85,R85,U85,X85,AA85,AD85,AG85) -> 605 | E85: 331990 | F85: 88 | G85: 1320 | H85: 1551197 | I85: 234 | J85: 3510 | K85: 295244 | L85: 75 | M85: 1125 | N85: 235216 | O85: 82 | P85: 1230 | Q85: 76484 | R85: 19 | S85: 285 | T85: 148961 | U85: 23 | V85: 345 | W85: 78903 | X85: 27 | Y85: 405 | Z85: 60684 | AA85: 16 | AB85: 240 | AC85: 75659 | AD85: 26 | AE85: 390 | AF85: 31039 | AG85: 15 | AH85: 225
B86: ชำระค่าต่ออายุสถานภาพ นศ.มสธ. | C86: 2929 | D86: =SUM(F86,I86,L86,O86,R86,U86,X86,AA86,AD86,AG86) -> 582 | E86: 10800 | F86: 36 | G86: 360 | H86: 16200 | I86: 54 | J86: 540 | K86: 20100 | L86: 67 | M86: 670 | N86: 22800 | O86: 76 | P86: 760 | Q86: 9300 | R86: 31 | S86: 310 | T86: 15000 | U86: 50 | V86: 500 | W86: 39900 | X86: 133 | Y86: 1330 | Z86: 18300 | AA86: 61 | AB86: 610 | AC86: 13800 | AD86: 46 | AE86: 460 | AF86: 8400 | AG86: 28 | AH86: 280
B87: ขึ้นทะเบียนมหาบัณฑิต บ.16 (ป.โท-เอก) | C87: 2883 | D87: =SUM(F87,I87,L87,O87,R87,U87,X87,AA87,AD87,AG87) -> 562 | E87: 81000 | F87: 81 | G87: 810 | H87: 38000 | I87: 38 | J87: 380 | K87: 61000 | L87: 61 | M87: 610 | N87: 94000 | O87: 94 | P87: 940 | Q87: 30000 | R87: 28 | S87: 280 | T87: 33000 | U87: 29 | V87: 290 | W87: 31000 | X87: 31 | Y87: 310 | Z87: 44000 | AA87: 44 | AB87: 440 | AC87: 97000 | AD87: 97 | AE87: 970 | AF87: 59000 | AG87: 59 | AH87: 590
B88: ชำระเบี้ยต่ออายุ บ.ไทยสมุทรประกันชีวิตฯ | C88: 30103 | D88: =SUM(F88,I88,L88,O88,R88,U88,X88,AA88,AD88,AG88) -> 511 | E88: 505629 | F88: 56 | G88: 840 | H88: 327160 | I88: 38 | J88: 570 | K88: 532072 | L88: 65 | M88: 975 | N88: 480294 | O88: 88 | P88: 1320 | Q88: 300426 | R88: 38 | S88: 570 | T88: 245835 | U88: 39 | V88: 585 | W88: 363517 | X88: 48 | Y88: 720 | Z88: 293733 | AA88: 36 | AB88: 540 | AC88: 373034 | AD88: 56 | AE88: 840 | AF88: 403317 | AG88: 47 | AH88: 705
B89: ชำระค่าบริการ บจ.ทรูมูฟเอช ยูนิเวอร์แซลฯ | C89: 3180 | D89: =SUM(F89,I89,L89,O89,R89,U89,X89,AA89,AD89,AG89) -> 494 | E89: 25681 | F89: 52 | G89: 780 | H89: 29329 | I89: 53 | J89: 795 | K89: 29698 | L89: 51 | M89: 765 | N89: 55010 | O89: 84 | P89: 1260 | Q89: 29336 | R89: 43 | S89: 645 | T89: 17099 | U89: 38 | V89: 570 | W89: 19622 | X89: 35 | Y89: 525 | Z89: 25195 | AA89: 46 | AB89: 690 | AC89: 27888 | AD89: 49 | AE89: 735 | AF89: 23276 | AG89: 43 | AH89: 645
B90: ชำระเงินสงเคราะห์ ฌปก. ลูกค้า ธกส.อำนาจเจริญ | C90: 366627 | D90: =SUM(F90,I90,L90,O90,R90,U90,X90,AA90,AD90,AG90) -> 468 | W90: 100 | X90: 1 | Y90: 10 | Z90: 230814 | AA90: 86 | AB90: 860 | AC90: 708221 | AD90: 265 | AE90: 2650 | AF90: 309294 | AG90: 116 | AH90: 1160
B91: ค่าบริการเพื่อกลุ่ม TRUE | C91: 3177 | D91: =SUM(F91,I91,L91,O91,R91,U91,X91,AA91,AD91,AG91) -> 416 | E91: 29533 | F91: 47 | G91: 705 | H91: 27367 | I91: 41 | J91: 615 | K91: 26790 | L91: 38 | M91: 570 | N91: 61577 | O91: 80 | P91: 1200 | Q91: 32463 | R91: 39 | S91: 585 | T91: 23950 | U91: 36 | V91: 540 | W91: 27494 | X91: 38 | Y91: 570 | Z91: 24751 | AA91: 32 | AB91: 480 | AC91: 25961 | AD91: 34 | AE91: 510 | AF91: 23930 | AG91: 31 | AH91: 465
B92: รับเงินฝาก ธ.เกียรตินาคินภัทร(คีย์เลขที่บ/ช) | C92: 2658 | D92: =SUM(F92,I92,L92,O92,R92,U92,X92,AA92,AD92,AG92) -> 403 | E92: 1364215 | F92: 55 | G92: 825 | H92: 797855 | I92: 36 | J92: 540 | K92: 756154 | L92: 33 | M92: 495 | N92: 1522607 | O92: 70 | P92: 1050 | Q92: 600899 | R92: 41 | S92: 615 | T92: 756845 | U92: 39 | V92: 585 | W92: 390696 | X92: 18 | Y92: 270 | Z92: 561800 | AA92: 24 | AB92: 360 | AC92: 763667 | AD92: 41 | AE92: 615 | AF92: 961160 | AG92: 46 | AH92: 690
B93: ชำระเงินกู้กยศ.บาร์สั้นไม่มีครบกำหนด KTB | C93: 30115 | D93: =SUM(F93,I93,L93,O93,R93,U93,X93,AA93,AD93,AG93) -> 397 | E93: 80571 | F93: 23 | G93: 230 | H93: 113091 | I93: 22 | J93: 220 | K93: 84796 | L93: 16 | M93: 160 | N93: 110619 | O93: 46 | P93: 460 | Q93: 35339 | R93: 21 | S93: 210 | T93: 110569 | U93: 33 | V93: 330 | W93: 460593 | X93: 74 | Y93: 740 | Z93: 162240 | AA93: 28 | AB93: 290 | AC93: 50682 | AD93: 23 | AE93: 230 | AF93: 586244 | AG93: 111 | AH93: 1110
B94: ชำระค่าสินเชื่อรถ พรประเสริฐออโต้ลีส | C94: 3153 | D94: =SUM(F94,I94,L94,O94,R94,U94,X94,AA94,AD94,AG94) -> 388 | E94: 63610 | F94: 35 | G94: 525 | H94: 66953 | I94: 38 | J94: 570 | K94: 59962 | L94: 36 | M94: 540 | N94: 101016 | O94: 60 | P94: 900 | Q94: 56942 | R94: 37 | S94: 555 | T94: 52084 | U94: 34 | V94: 510 | W94: 58349 | X94: 36 | Y94: 540 | Z94: 54113 | AA94: 38 | AB94: 570 | AC94: 49433 | AD94: 35 | AE94: 525 | AF94: 64135 | AG94: 39 | AH94: 585
B95: รับชำระ เฮงลิสซิ่ง | C95: 363834 | D95: =SUM(F95,I95,L95,O95,R95,U95,X95,AA95,AD95,AG95) -> 382 | E95: 165849 | F95: 37 | G95: 370 | H95: 129992 | I95: 42 | J95: 420 | K95: 131501 | L95: 41 | M95: 410 | N95: 291822 | O95: 70 | P95: 700 | Q95: 142025 | R95: 36 | S95: 360 | T95: 170743 | U95: 38 | V95: 380 | W95: 95763 | X95: 32 | Y95: 320 | Z95: 103731 | AA95: 32 | AB95: 320 | AC95: 90350 | AD95: 28 | AE95: 280 | AF95: 72479 | AG95: 26 | AH95: 260
B96: สินเชื่อบุคคล-ที่อยู่อาศัยกรุงศรีอยุธยา | C96: 3004 | D96: =SUM(F96,I96,L96,O96,R96,U96,X96,AA96,AD96,AG96) -> 369 | E96: 272609 | F96: 34 | G96: 340 | H96: 274459 | I96: 30 | J96: 310 | K96: 271816 | L96: 37 | M96: 370 | N96: 496790 | O96: 66 | P96: 660 | Q96: 303686 | R96: 32 | S96: 320 | T96: 245420 | U96: 33 | V96: 330 | W96: 378523 | X96: 38 | Y96: 380 | Z96: 306442 | AA96: 32 | AB96: 340 | AC96: 299306 | AD96: 32 | AE96: 320 | AF96: 330943 | AG96: 35 | AH96: 350
B97: ชำระค่าสินค้า บริษัท ซิลลิค ฟาร์มา | C97: 2849 | D97: =SUM(F97,I97,L97,O97,R97,U97,X97,AA97,AD97,AG97) -> 354 | E97: 1502375 | F97: 66 | G97: 990 | H97: 369289 | I97: 27 | J97: 405 | K97: 284174 | L97: 21 | M97: 315 | N97: 2132034 | O97: 88 | P97: 1320 | Q97: 658846 | R97: 28 | S97: 420 | T97: 708794 | U97: 32 | V97: 480 | W97: 565634 | X97: 31 | Y97: 465 | Z97: 471762 | AA97: 24 | AB97: 360 | AC97: 550499 | AD97: 19 | AE97: 285 | AF97: 364209 | AG97: 18 | AH97: 270
B98: ค่าบริการทรู อินเทอร์เน็ต คอร์ป | C98: 30102 | D98: =SUM(F98,I98,L98,O98,R98,U98,X98,AA98,AD98,AG98) -> 337 | E98: 21283 | F98: 34 | G98: 510 | H98: 19950 | I98: 25 | J98: 375 | K98: 22040 | L98: 29 | M98: 435 | N98: 45891 | O98: 58 | P98: 870 | Q98: 21411 | R98: 31 | S98: 465 | T98: 28550 | U98: 37 | V98: 555 | W98: 22366 | X98: 34 | Y98: 510 | Z98: 14481 | AA98: 22 | AB98: 330 | AC98: 24977 | AD98: 28 | AE98: 420 | AF98: 26469 | AG98: 39 | AH98: 585
B99: ต่อประกันภัยรถยนต์ โตโยต้า อินชัวรันซ์ | C99: 3010 | D99: =SUM(F99,I99,L99,O99,R99,U99,X99,AA99,AD99,AG99) -> 323 | E99: 409882 | F99: 49 | G99: 735 | H99: 403131 | I99: 49 | J99: 735 | K99: 347185 | L99: 41 | M99: 615 | N99: 439103 | O99: 50 | P99: 750 | Q99: 220706 | R99: 24 | S99: 360 | T99: 178279 | U99: 16 | V99: 240 | W99: 213588 | X99: 20 | Y99: 300 | Z99: 235164 | AA99: 26 | AB99: 390 | AC99: 197828 | AD99: 20 | AE99: 300 | AF99: 342771 | AG99: 28 | AH99: 420
B100: ลงทะเบียนบัณฑิตศึกษา มสธ. (ป.โท) | C100: 2882 | D100: =SUM(F100,I100,L100,O100,R100,U100,X100,AA100,AD100,AG100) -> 305 | E100: 839800 | F100: 79 | G100: 790 | H100: 214800 | I100: 31 | J100: 310 | K100: 236100 | L100: 42 | M100: 420 | N100: 167000 | O100: 22 | P100: 220 | Q100: 2000 | R100: 1 | S100: 10 | T100: 32700 | U100: 7 | V100: 70 | W100: 1983900 | X100: 105 | Y100: 1050 | Z100: 78400 | AA100: 8 | AB100: 80 | AC100: 32500 | AD100: 6 | AE100: 60 | AF100: 16400 | AG100: 4 | AH100: 40
B101: ประกันชีวิต บมจ.อลิอันซ์ อยุธยา | C101: 2990 | D101: =SUM(F101,I101,L101,O101,R101,U101,X101,AA101,AD101,AG101) -> 292 | E101: 234399 | F101: 33 | G101: 660 | H101: 225557 | I101: 25 | J101: 500 | K101: 175423 | L101: 26 | M101: 520 | N101: 392615 | O101: 48 | P101: 960 | Q101: 119188 | R101: 15 | S101: 300 | T101: 216033 | U101: 27 | V101: 540 | W101: 183389 | X101: 21 | Y101: 420 | Z101: 271207 | AA101: 38 | AB101: 760 | AC101: 229891 | AD101: 29 | AE101: 580 | AF101: 323799 | AG101: 30 | AH101: 600
B102: ชำระค่าสินค้า-บริการเครือCITIGROUPมีบาร์ | C102: 3049 | D102: =SUM(F102,I102,L102,O102,R102,U102,X102,AA102,AD102,AG102) -> 289 | E102: 215145 | F102: 22 | G102: 330 | H102: 244343 | I102: 23 | J102: 345 | K102: 395099 | L102: 34 | M102: 510 | N102: 629102 | O102: 58 | P102: 870 | Q102: 279430 | R102: 24 | S102: 360 | T102: 256956 | U102: 25 | V102: 375 | W102: 209195 | X102: 29 | Y102: 435 | Z102: 106343 | AA102: 14 | AB102: 210 | AC102: 324026 | AD102: 30 | AE102: 450 | AF102: 515235 | AG102: 30 | AH102: 450
B103: ชำระเงินสงเคราะห์ ฌกฝ. ผู้ฝากเงิน ธกส.อำนาจเจริญ | C103: 366629 | D103: =SUM(F103,I103,L103,O103,R103,U103,X103,AA103,AD103,AG103) -> 289 | W103: 100 | X103: 2 | Y103: 20 | Z103: 204329 | AA103: 61 | AB103: 610 | AC103: 526809 | AD103: 159 | AE103: 1590 | AF103: 213526 | AG103: 67 | AH103: 670
B104: ชำระค่าเบี้ยประกัน กรุงเทพประกันภัย | C104: 2782 | D104: =SUM(F104,I104,L104,O104,R104,U104,X104,AA104,AD104,AG104) -> 284 | E104: 142849 | F104: 26 | G104: 390 | H104: 140575 | I104: 32 | J104: 480 | K104: 74571 | L104: 30 | M104: 450 | N104: 200856 | O104: 54 | P104: 810 | Q104: 56196 | R104: 24 | S104: 360 | T104: 147559 | U104: 24 | V104: 360 | W104: 60998 | X104: 25 | Y104: 375 | Z104: 59236 | AA104: 26 | AB104: 390 | AC104: 115238 | AD104: 18 | AE104: 270 | AF104: 172706 | AG104: 25 | AH104: 375
B105: ชำระเงินสำหรับการเคหะแห่งชาติออนไลน์ | C105: 3197 | D105: =SUM(F105,I105,L105,O105,R105,U105,X105,AA105,AD105,AG105) -> 271 | E105: 94787 | F105: 29 | G105: 290 | H105: 81912 | I105: 26 | J105: 260 | K105: 81886 | L105: 25 | M105: 250 | N105: 131426 | O105: 44 | P105: 440 | Q105: 100664 | R105: 28 | S105: 280 | T105: 77180 | U105: 25 | V105: 250 | W105: 88061 | X105: 28 | Y105: 280 | Z105: 76101 | AA105: 25 | AB105: 250 | AC105: 72801 | AD105: 22 | AE105: 220 | AF105: 64040 | AG105: 19 | AH105: 190
B106: ชำระค่าขอวีซ่าสถานฑูตสหรัฐอเมริกา (Aramex) | C106: 366915 | D106: =SUM(F106,I106,L106,O106,R106,U106,X106,AA106,AD106,AG106) -> 250 | Z106: 1200 | AA106: 3 | AB106: 0 | AF106: 98800 | AG106: 247 | AH106: 0
B107: ชำระค่าเบี้ยประกัน บ.ธนชาตโบรกเกอร์ | C107: 3136 | D107: =SUM(F107,I107,L107,O107,R107,U107,X107,AA107,AD107,AG107) -> 246 | E107: 210636 | F107: 27 | G107: 405 | H107: 127137 | I107: 20 | J107: 300 | K107: 266426 | L107: 32 | M107: 480 | N107: 360547 | O107: 48 | P107: 720 | Q107: 131874 | R107: 16 | S107: 240 | T107: 151864 | U107: 21 | V107: 315 | W107: 94997 | X107: 14 | Y107: 210 | Z107: 182908 | AA107: 27 | AB107: 405 | AC107: 142590 | AD107: 21 | AE107: 315 | AF107: 121648 | AG107: 20 | AH107: 300
B108: คำร้องต่าง ๆ (ป.โท-เอก) | C108: 2881 | D108: =SUM(F108,I108,L108,O108,R108,U108,X108,AA108,AD108,AG108) -> 235 | E108: 9700 | F108: 30 | G108: 300 | H108: 12800 | I108: 23 | J108: 230 | K108: 5300 | L108: 21 | M108: 210 | N108: 8400 | O108: 34 | P108: 340 | Q108: 9100 | R108: 23 | S108: 230 | T108: 11500 | U108: 28 | V108: 280 | W108: 13000 | X108: 27 | Y108: 270 | Z108: 4600 | AA108: 16 | AB108: 160 | AC108: 7200 | AD108: 18 | AE108: 180 | AF108: 5500 | AG108: 15 | AH108: 150
B109: ชำระเบี้ยประกันภัยเจมาร์ท Jaymart | C109: 364822 | D109: =SUM(F109,I109,L109,O109,R109,U109,X109,AA109,AD109,AG109) -> 230 | E109: 4380 | F109: 14 | G109: 0 | H109: 4250 | I109: 14 | J109: 0 | K109: 9080 | L109: 33 | M109: 0 | N109: 29011 | O109: 86 | P109: 0 | Q109: 5650 | R109: 18 | S109: 0 | T109: 5000 | U109: 18 | V109: 0 | W109: 6695 | X109: 22 | Y109: 0 | Z109: 5072 | AA109: 13 | AB109: 0 | AC109: 3275 | AD109: 10 | AE109: 0 | AF109: 570 | AG109: 2 | AH109: 0
B110: ชำระค่าธรรมเนียมการตรวจบทคัดย่อฯ มสธ. | C110: 2670 | D110: =SUM(F110,I110,L110,O110,R110,U110,X110,AA110,AD110,AG110) -> 229 | E110: 4800 | F110: 16 | G110: 160 | H110: 4800 | I110: 16 | J110: 160 | K110: 12000 | L110: 40 | M110: 400 | N110: 4200 | O110: 14 | P110: 140 | Q110: 2700 | R110: 9 | S110: 90 | T110: 1800 | U110: 6 | V110: 60 | W110: 2400 | X110: 8 | Y110: 80 | Z110: 6000 | AA110: 20 | AB110: 200 | AC110: 16800 | AD110: 56 | AE110: 560 | AF110: 13200 | AG110: 44 | AH110: 440
B111: ถอนเงิน ธ.ไทยพาณิชย์ จำกัด | C111: 357648 | D111: =SUM(F111,I111,L111,O111,R111,U111,X111,AA111,AD111,AG111) -> 227 | E111: -78023 | F111: 19 | G111: 0 | H111: -107790 | I111: 30 | J111: 0 | K111: -46698 | L111: 17 | M111: 0 | N111: -63332 | O111: 24 | P111: 0 | Q111: -61300 | R111: 23 | S111: 0 | T111: -76897 | U111: 23 | V111: 0 | W111: -71300 | X111: 19 | Y111: 0 | Z111: -41500 | AA111: 13 | AB111: 0 | AC111: -51680 | AD111: 18 | AE111: 0 | AF111: -52390 | AG111: 41 | AH111: 0
B112: ชำระค่าเบี้ยไมโคร 200 บ.วิริยะประกันฯ | C112: 3192 | D112: =SUM(F112,I112,L112,O112,R112,U112,X112,AA112,AD112,AG112) -> 223 | E112: 12600 | F112: 63 | G112: 0 | H112: 3000 | I112: 15 | J112: 0 | K112: 2800 | L112: 14 | M112: 0 | N112: 5600 | O112: 28 | P112: 0 | Q112: 7000 | R112: 35 | S112: 0 | T112: 1800 | U112: 9 | V112: 0 | W112: 3200 | X112: 16 | Y112: 0 | Z112: 1200 | AA112: 6 | AB112: 0 | AC112: 4600 | AD112: 23 | AE112: 0 | AF112: 2800 | AG112: 14 | AH112: 0
...
